{
  "vehicle_id": "SE1_KA04AB5794_JETTING",
  "date": "2023-08-12",
  "points": [
    {
      "timestamp": "2023-08-12T09:20:00",
      "lat": 12.953277,
      "lon": 77.611805
    },
    {
      "timestamp": "2023-08-12T09:20:15",
      "lat": 12.953378,
      "lon": 77.611494
    },
    {
      "timestamp": "2023-08-12T09:20:31",
      "lat": 12.953593,
      "lon": 77.611412
    },
    {
      "timestamp": "2023-08-12T09:20:56",
      "lat": 12.953901,
      "lon": 77.611518
    },
    {
      "timestamp": "2023-08-12T09:21:18",
      "lat": 12.95416,
      "lon": 77.611511
    },
    {
      "timestamp": "2023-08-12T09:21:41",
      "lat": 12.954269,
      "lon": 77.611204
    },
    {
      "timestamp": "2023-08-12T09:22:03",
      "lat": 12.954356,
      "lon": 77.61089
    },
    {
      "timestamp": "2023-08-12T09:22:28",
      "lat": 12.954444,
      "lon": 77.610575
    },
    {
      "timestamp": "2023-08-12T09:22:44",
      "lat": 12.954748,
      "lon": 77.610634
    },
    {
      "timestamp": "2023-08-12T09:23:00",
      "lat": 12.955064,
      "lon": 77.610716
    },
    {
      "timestamp": "2023-08-12T09:23:22",
      "lat": 12.95538,
      "lon": 77.610797
    },
    {
      "timestamp": "2023-08-12T09:23:40",
      "lat": 12.955702,
      "lon": 77.610835
    },
    {
      "timestamp": "2023-08-12T09:23:56",
      "lat": 12.956028,
      "lon": 77.610832
    },
    {
      "timestamp": "2023-08-12T09:24:21",
      "lat": 12.956355,
      "lon": 77.610828
    },
    {
      "timestamp": "2023-08-12T09:24:44",
      "lat": 12.956681,
      "lon": 77.610825
    },
    {
      "timestamp": "2023-08-12T09:25:06",
      "lat": 12.957008,
      "lon": 77.610822
    },
    {
      "timestamp": "2023-08-12T09:25:21",
      "lat": 12.957334,
      "lon": 77.610819
    },
    {
      "timestamp": "2023-08-12T09:25:38",
      "lat": 12.957661,
      "lon": 77.610816
    },
    {
      "timestamp": "2023-08-12T09:25:59",
      "lat": 12.957987,
      "lon": 77.610812
    },
    {
      "timestamp": "2023-08-12T09:26:16",
      "lat": 12.958314,
      "lon": 77.610809
    },
    {
      "timestamp": "2023-08-12T09:26:38",
      "lat": 12.95864,
      "lon": 77.610814
    },
    {
      "timestamp": "2023-08-12T09:27:00",
      "lat": 12.958915,
      "lon": 77.610932
    },
    {
      "timestamp": "2023-08-12T09:27:15",
      "lat": 12.95892,
      "lon": 77.611253
    },
    {
      "timestamp": "2023-08-12T09:27:30",
      "lat": 12.95891,
      "lon": 77.611579
    },
    {
      "timestamp": "2023-08-12T09:27:48",
      "lat": 12.9589,
      "lon": 77.611906
    },
    {
      "timestamp": "2023-08-12T09:28:13",
      "lat": 12.958813,
      "lon": 77.612143
    },
    {
      "timestamp": "2023-08-12T09:28:35",
      "lat": 12.958489,
      "lon": 77.612103
    },
    {
      "timestamp": "2023-08-12T09:28:57",
      "lat": 12.958429,
      "lon": 77.612399
    },
    {
      "timestamp": "2023-08-12T09:29:13",
      "lat": 12.958392,
      "lon": 77.612723
    },
    {
      "timestamp": "2023-08-12T09:29:31",
      "lat": 12.958355,
      "lon": 77.613048
    },
    {
      "timestamp": "2023-08-12T09:29:53",
      "lat": 12.958317,
      "lon": 77.613372
    },
    {
      "timestamp": "2023-08-12T09:30:16",
      "lat": 12.95828,
      "lon": 77.613696
    },
    {
      "timestamp": "2023-08-12T09:30:31",
      "lat": 12.958243,
      "lon": 77.614021
    },
    {
      "timestamp": "2023-08-12T09:30:48",
      "lat": 12.958205,
      "lon": 77.614345
    },
    {
      "timestamp": "2023-08-12T09:31:08",
      "lat": 12.958165,
      "lon": 77.614669
    },
    {
      "timestamp": "2023-08-12T09:31:28",
      "lat": 12.958124,
      "lon": 77.614993
    },
    {
      "timestamp": "2023-08-12T09:31:47",
      "lat": 12.95809,
      "lon": 77.615318
    },
    {
      "timestamp": "2023-08-12T09:32:12",
      "lat": 12.958055,
      "lon": 77.615643
    },
    {
      "timestamp": "2023-08-12T09:32:33",
      "lat": 12.95802,
      "lon": 77.615967
    },
    {
      "timestamp": "2023-08-12T09:32:50",
      "lat": 12.957985,
      "lon": 77.616292
    },
    {
      "timestamp": "2023-08-12T09:33:13",
      "lat": 12.95796,
      "lon": 77.616618
    },
    {
      "timestamp": "2023-08-12T09:33:28",
      "lat": 12.957638,
      "lon": 77.616651
    },
    {
      "timestamp": "2023-08-12T09:33:44",
      "lat": 12.957313,
      "lon": 77.616681
    },
    {
      "timestamp": "2023-08-12T09:34:02",
      "lat": 12.957043,
      "lon": 77.616801
    },
    {
      "timestamp": "2023-08-12T09:34:24",
      "lat": 12.95705,
      "lon": 77.617126
    },
    {
      "timestamp": "2023-08-12T09:34:47",
      "lat": 12.956988,
      "lon": 77.617446
    },
    {
      "timestamp": "2023-08-12T09:35:10",
      "lat": 12.956754,
      "lon": 77.617662
    },
    {
      "timestamp": "2023-08-12T09:35:32",
      "lat": 12.956486,
      "lon": 77.617848
    },
    {
      "timestamp": "2023-08-12T09:35:48",
      "lat": 12.956408,
      "lon": 77.618119
    },
    {
      "timestamp": "2023-08-12T09:36:10",
      "lat": 12.956466,
      "lon": 77.61844
    },
    {
      "timestamp": "2023-08-12T09:36:26",
      "lat": 12.956525,
      "lon": 77.618762
    },
    {
      "timestamp": "2023-08-12T09:36:49",
      "lat": 12.956678,
      "lon": 77.619022
    },
    {
      "timestamp": "2023-08-12T09:37:04",
      "lat": 12.956622,
      "lon": 77.619294
    },
    {
      "timestamp": "2023-08-12T09:37:26",
      "lat": 12.956591,
      "lon": 77.619617
    },
    {
      "timestamp": "2023-08-12T09:37:47",
      "lat": 12.956591,
      "lon": 77.619944
    },
    {
      "timestamp": "2023-08-12T09:38:02",
      "lat": 12.956589,
      "lon": 77.62027
    },
    {
      "timestamp": "2023-08-12T09:38:27",
      "lat": 12.956586,
      "lon": 77.620597
    },
    {
      "timestamp": "2023-08-12T09:38:47",
      "lat": 12.956584,
      "lon": 77.620923
    },
    {
      "timestamp": "2023-08-12T09:39:10",
      "lat": 12.95646,
      "lon": 77.621102
    },
    {
      "timestamp": "2023-08-12T09:39:31",
      "lat": 12.956167,
      "lon": 77.621066
    },
    {
      "timestamp": "2023-08-12T09:39:47",
      "lat": 12.956247,
      "lon": 77.621379
    },
    {
      "timestamp": "2023-08-12T09:40:02",
      "lat": 12.95639,
      "lon": 77.621672
    },
    {
      "timestamp": "2023-08-12T09:40:25",
      "lat": 12.956516,
      "lon": 77.621973
    },
    {
      "timestamp": "2023-08-12T09:40:46",
      "lat": 12.956682,
      "lon": 77.622176
    },
    {
      "timestamp": "2023-08-12T09:41:04",
      "lat": 12.956829,
      "lon": 77.622425
    },
    {
      "timestamp": "2023-08-12T09:41:19",
      "lat": 12.957125,
      "lon": 77.622288
    },
    {
      "timestamp": "2023-08-12T09:41:42",
      "lat": 12.957422,
      "lon": 77.622151
    },
    {
      "timestamp": "2023-08-12T09:41:57",
      "lat": 12.957721,
      "lon": 77.62202
    },
    {
      "timestamp": "2023-08-12T09:42:19",
      "lat": 12.957853,
      "lon": 77.622299
    },
    {
      "timestamp": "2023-08-12T09:42:40",
      "lat": 12.957974,
      "lon": 77.622602
    },
    {
      "timestamp": "2023-08-12T09:43:04",
      "lat": 12.958096,
      "lon": 77.622905
    },
    {
      "timestamp": "2023-08-12T09:43:29",
      "lat": 12.958217,
      "lon": 77.623209
    },
    {
      "timestamp": "2023-08-12T09:43:44",
      "lat": 12.958339,
      "lon": 77.623512
    },
    {
      "timestamp": "2023-08-12T09:44:03",
      "lat": 12.958461,
      "lon": 77.623815
    },
    {
      "timestamp": "2023-08-12T09:44:26",
      "lat": 12.958354,
      "lon": 77.623549
    },
    {
      "timestamp": "2023-08-12T09:44:48",
      "lat": 12.958232,
      "lon": 77.623246
    },
    {
      "timestamp": "2023-08-12T09:45:06",
      "lat": 12.958111,
      "lon": 77.622943
    },
    {
      "timestamp": "2023-08-12T09:45:21",
      "lat": 12.957989,
      "lon": 77.62264
    },
    {
      "timestamp": "2023-08-12T09:45:46",
      "lat": 12.957868,
      "lon": 77.622337
    },
    {
      "timestamp": "2023-08-12T09:46:01",
      "lat": 12.957746,
      "lon": 77.622033
    },
    {
      "timestamp": "2023-08-12T09:46:20",
      "lat": 12.957459,
      "lon": 77.622135
    },
    {
      "timestamp": "2023-08-12T09:46:42",
      "lat": 12.957162,
      "lon": 77.622271
    },
    {
      "timestamp": "2023-08-12T09:47:00",
      "lat": 12.956865,
      "lon": 77.622408
    },
    {
      "timestamp": "2023-08-12T09:47:15",
      "lat": 12.956697,
      "lon": 77.622214
    },
    {
      "timestamp": "2023-08-12T09:47:35",
      "lat": 12.95653,
      "lon": 77.622011
    },
    {
      "timestamp": "2023-08-12T09:48:00",
      "lat": 12.956406,
      "lon": 77.621709
    },
    {
      "timestamp": "2023-08-12T09:48:23",
      "lat": 12.956266,
      "lon": 77.621414
    },
    {
      "timestamp": "2023-08-12T09:48:44",
      "lat": 12.956171,
      "lon": 77.621106
    },
    {
      "timestamp": "2023-08-12T09:49:01",
      "lat": 12.955909,
      "lon": 77.620987
    },
    {
      "timestamp": "2023-08-12T09:49:17",
      "lat": 12.955588,
      "lon": 77.620925
    },
    {
      "timestamp": "2023-08-12T09:49:34",
      "lat": 12.955273,
      "lon": 77.620856
    },
    {
      "timestamp": "2023-08-12T09:49:52",
      "lat": 12.954955,
      "lon": 77.62078
    },
    {
      "timestamp": "2023-08-12T09:50:07",
      "lat": 12.954638,
      "lon": 77.620703
    },
    {
      "timestamp": "2023-08-12T09:50:31",
      "lat": 12.954327,
      "lon": 77.620605
    },
    {
      "timestamp": "2023-08-12T09:50:46",
      "lat": 12.954013,
      "lon": 77.620513
    },
    {
      "timestamp": "2023-08-12T09:51:10",
      "lat": 12.953699,
      "lon": 77.620426
    },
    {
      "timestamp": "2023-08-12T09:51:28",
      "lat": 12.953381,
      "lon": 77.620351
    },
    {
      "timestamp": "2023-08-12T09:51:44",
      "lat": 12.953063,
      "lon": 77.620276
    },
    {
      "timestamp": "2023-08-12T09:52:07",
      "lat": 12.952742,
      "lon": 77.620218
    },
    {
      "timestamp": "2023-08-12T09:52:30",
      "lat": 12.952422,
      "lon": 77.620213
    },
    {
      "timestamp": "2023-08-12T09:52:54",
      "lat": 12.952265,
      "lon": 77.620497
    },
    {
      "timestamp": "2023-08-12T09:53:10",
      "lat": 12.952112,
      "lon": 77.620785
    },
    {
      "timestamp": "2023-08-12T09:53:25",
      "lat": 12.951959,
      "lon": 77.621074
    },
    {
      "timestamp": "2023-08-12T09:53:44",
      "lat": 12.951806,
      "lon": 77.621362
    },
    {
      "timestamp": "2023-08-12T09:54:03",
      "lat": 12.951557,
      "lon": 77.621398
    },
    {
      "timestamp": "2023-08-12T09:54:18",
      "lat": 12.951251,
      "lon": 77.621284
    },
    {
      "timestamp": "2023-08-12T09:54:38",
      "lat": 12.950945,
      "lon": 77.621171
    },
    {
      "timestamp": "2023-08-12T09:54:58",
      "lat": 12.950643,
      "lon": 77.621046
    },
    {
      "timestamp": "2023-08-12T09:55:22",
      "lat": 12.950352,
      "lon": 77.620898
    },
    {
      "timestamp": "2023-08-12T09:55:45",
      "lat": 12.950066,
      "lon": 77.620742
    },
    {
      "timestamp": "2023-08-12T09:56:01",
      "lat": 12.949781,
      "lon": 77.620583
    },
    {
      "timestamp": "2023-08-12T09:56:18",
      "lat": 12.949495,
      "lon": 77.620424
    },
    {
      "timestamp": "2023-08-12T09:56:43",
      "lat": 12.94921,
      "lon": 77.620264
    },
    {
      "timestamp": "2023-08-12T09:56:59",
      "lat": 12.948926,
      "lon": 77.620104
    },
    {
      "timestamp": "2023-08-12T09:57:16",
      "lat": 12.94864,
      "lon": 77.619946
    },
    {
      "timestamp": "2023-08-12T09:57:35",
      "lat": 12.948355,
      "lon": 77.619788
    },
    {
      "timestamp": "2023-08-12T09:57:58",
      "lat": 12.94807,
      "lon": 77.619628
    },
    {
      "timestamp": "2023-08-12T09:58:18",
      "lat": 12.947786,
      "lon": 77.619467
    },
    {
      "timestamp": "2023-08-12T09:58:36",
      "lat": 12.947498,
      "lon": 77.619313
    },
    {
      "timestamp": "2023-08-12T09:58:53",
      "lat": 12.94721,
      "lon": 77.61916
    },
    {
      "timestamp": "2023-08-12T09:59:12",
      "lat": 12.946923,
      "lon": 77.619003
    },
    {
      "timestamp": "2023-08-12T09:59:36",
      "lat": 12.946636,
      "lon": 77.618848
    },
    {
      "timestamp": "2023-08-12T09:59:55",
      "lat": 12.946349,
      "lon": 77.618692
    },
    {
      "timestamp": "2023-08-12T10:00:17",
      "lat": 12.94604,
      "lon": 77.618589
    },
    {
      "timestamp": "2023-08-12T10:00:33",
      "lat": 12.945753,
      "lon": 77.618689
    },
    {
      "timestamp": "2023-08-12T10:00:57",
      "lat": 12.945547,
      "lon": 77.618942
    },
    {
      "timestamp": "2023-08-12T10:01:15",
      "lat": 12.945346,
      "lon": 77.6192
    },
    {
      "timestamp": "2023-08-12T10:01:40",
      "lat": 12.945043,
      "lon": 77.61913
    },
    {
      "timestamp": "2023-08-12T10:02:01",
      "lat": 12.94473,
      "lon": 77.619037
    },
    {
      "timestamp": "2023-08-12T10:02:26",
      "lat": 12.944415,
      "lon": 77.618953
    },
    {
      "timestamp": "2023-08-12T10:02:47",
      "lat": 12.944098,
      "lon": 77.618874
    },
    {
      "timestamp": "2023-08-12T10:03:07",
      "lat": 12.94378,
      "lon": 77.6188
    },
    {
      "timestamp": "2023-08-12T10:03:25",
      "lat": 12.943461,
      "lon": 77.61874
    },
    {
      "timestamp": "2023-08-12T10:03:44",
      "lat": 12.943366,
      "lon": 77.619051
    },
    {
      "timestamp": "2023-08-12T10:04:00",
      "lat": 12.943205,
      "lon": 77.619332
    },
    {
      "timestamp": "2023-08-12T10:04:24",
      "lat": 12.942988,
      "lon": 77.619575
    },
    {
      "timestamp": "2023-08-12T10:04:39",
      "lat": 12.942719,
      "lon": 77.619761
    },
    {
      "timestamp": "2023-08-12T10:05:01",
      "lat": 12.942405,
      "lon": 77.619771
    },
    {
      "timestamp": "2023-08-12T10:05:20",
      "lat": 12.942118,
      "lon": 77.619615
    },
    {
      "timestamp": "2023-08-12T10:05:40",
      "lat": 12.941854,
      "lon": 77.619425
    },
    {
      "timestamp": "2023-08-12T10:06:04",
      "lat": 12.941639,
      "lon": 77.619181
    },
    {
      "timestamp": "2023-08-12T10:06:29",
      "lat": 12.941491,
      "lon": 77.61889
    },
    {
      "timestamp": "2023-08-12T10:06:45",
      "lat": 12.941284,
      "lon": 77.618762
    },
    {
      "timestamp": "2023-08-12T10:07:06",
      "lat": 12.941137,
      "lon": 77.619054
    },
    {
      "timestamp": "2023-08-12T10:07:31",
      "lat": 12.940982,
      "lon": 77.619341
    },
    {
      "timestamp": "2023-08-12T10:07:48",
      "lat": 12.940827,
      "lon": 77.619628
    },
    {
      "timestamp": "2023-08-12T10:08:05",
      "lat": 12.940672,
      "lon": 77.619916
    },
    {
      "timestamp": "2023-08-12T10:08:28",
      "lat": 12.940519,
      "lon": 77.620204
    },
    {
      "timestamp": "2023-08-12T10:08:52",
      "lat": 12.940333,
      "lon": 77.620466
    },
    {
      "timestamp": "2023-08-12T10:09:08",
      "lat": 12.940099,
      "lon": 77.620695
    },
    {
      "timestamp": "2023-08-12T10:09:31",
      "lat": 12.940181,
      "lon": 77.620615
    },
    {
      "timestamp": "2023-08-12T10:09:52",
      "lat": 12.940414,
      "lon": 77.620386
    },
    {
      "timestamp": "2023-08-12T10:10:16",
      "lat": 12.940573,
      "lon": 77.620103
    },
    {
      "timestamp": "2023-08-12T10:10:33",
      "lat": 12.940726,
      "lon": 77.619815
    },
    {
      "timestamp": "2023-08-12T10:10:57",
      "lat": 12.940881,
      "lon": 77.619527
    },
    {
      "timestamp": "2023-08-12T10:11:17",
      "lat": 12.940683,
      "lon": 77.619328
    },
    {
      "timestamp": "2023-08-12T10:11:32",
      "lat": 12.94063,
      "lon": 77.619087
    },
    {
      "timestamp": "2023-08-12T10:11:57",
      "lat": 12.940773,
      "lon": 77.618793
    },
    {
      "timestamp": "2023-08-12T10:12:18",
      "lat": 12.940916,
      "lon": 77.6185
    },
    {
      "timestamp": "2023-08-12T10:12:41",
      "lat": 12.94101,
      "lon": 77.618188
    },
    {
      "timestamp": "2023-08-12T10:13:01",
      "lat": 12.941074,
      "lon": 77.617869
    },
    {
      "timestamp": "2023-08-12T10:13:18",
      "lat": 12.941085,
      "lon": 77.617543
    },
    {
      "timestamp": "2023-08-12T10:13:41",
      "lat": 12.94118,
      "lon": 77.617322
    },
    {
      "timestamp": "2023-08-12T10:14:00",
      "lat": 12.941389,
      "lon": 77.617212
    },
    {
      "timestamp": "2023-08-12T10:14:16",
      "lat": 12.941415,
      "lon": 77.616887
    },
    {
      "timestamp": "2023-08-12T10:14:32",
      "lat": 12.941441,
      "lon": 77.616561
    },
    {
      "timestamp": "2023-08-12T10:14:55",
      "lat": 12.941467,
      "lon": 77.616236
    },
    {
      "timestamp": "2023-08-12T10:15:11",
      "lat": 12.941772,
      "lon": 77.616197
    },
    {
      "timestamp": "2023-08-12T10:15:35",
      "lat": 12.941811,
      "lon": 77.615875
    },
    {
      "timestamp": "2023-08-12T10:15:57",
      "lat": 12.941915,
      "lon": 77.615569
    },
    {
      "timestamp": "2023-08-12T10:16:22",
      "lat": 12.942075,
      "lon": 77.615284
    },
    {
      "timestamp": "2023-08-12T10:16:42",
      "lat": 12.942208,
      "lon": 77.614986
    },
    {
      "timestamp": "2023-08-12T10:17:05",
      "lat": 12.942347,
      "lon": 77.614691
    },
    {
      "timestamp": "2023-08-12T10:17:27",
      "lat": 12.942493,
      "lon": 77.614399
    },
    {
      "timestamp": "2023-08-12T10:17:44",
      "lat": 12.942632,
      "lon": 77.614103
    },
    {
      "timestamp": "2023-08-12T10:18:03",
      "lat": 12.942746,
      "lon": 77.613798
    },
    {
      "timestamp": "2023-08-12T10:18:24",
      "lat": 12.942849,
      "lon": 77.613488
    },
    {
      "timestamp": "2023-08-12T10:18:48",
      "lat": 12.942975,
      "lon": 77.613191
    },
    {
      "timestamp": "2023-08-12T10:19:09",
      "lat": 12.943133,
      "lon": 77.612911
    },
    {
      "timestamp": "2023-08-12T10:19:26",
      "lat": 12.943239,
      "lon": 77.612603
    },
    {
      "timestamp": "2023-08-12T10:19:41",
      "lat": 12.943329,
      "lon": 77.612289
    },
    {
      "timestamp": "2023-08-12T10:19:57",
      "lat": 12.943403,
      "lon": 77.611972
    },
    {
      "timestamp": "2023-08-12T10:20:21",
      "lat": 12.943431,
      "lon": 77.611646
    },
    {
      "timestamp": "2023-08-12T10:20:41",
      "lat": 12.943525,
      "lon": 77.611333
    },
    {
      "timestamp": "2023-08-12T10:20:59",
      "lat": 12.943619,
      "lon": 77.611021
    },
    {
      "timestamp": "2023-08-12T10:21:14",
      "lat": 12.943757,
      "lon": 77.610727
    },
    {
      "timestamp": "2023-08-12T10:21:39",
      "lat": 12.943899,
      "lon": 77.610436
    },
    {
      "timestamp": "2023-08-12T10:22:04",
      "lat": 12.943965,
      "lon": 77.610116
    },
    {
      "timestamp": "2023-08-12T10:22:24",
      "lat": 12.944041,
      "lon": 77.609799
    },
    {
      "timestamp": "2023-08-12T10:22:47",
      "lat": 12.944115,
      "lon": 77.609481
    },
    {
      "timestamp": "2023-08-12T10:23:09",
      "lat": 12.944143,
      "lon": 77.609157
    },
    {
      "timestamp": "2023-08-12T10:23:24",
      "lat": 12.944165,
      "lon": 77.608853
    },
    {
      "timestamp": "2023-08-12T10:23:42",
      "lat": 12.943988,
      "lon": 77.608717
    },
    {
      "timestamp": "2023-08-12T10:23:58",
      "lat": 12.944001,
      "lon": 77.608391
    },
    {
      "timestamp": "2023-08-12T10:24:18",
      "lat": 12.944018,
      "lon": 77.608065
    },
    {
      "timestamp": "2023-08-12T10:24:43",
      "lat": 12.944003,
      "lon": 77.607744
    },
    {
      "timestamp": "2023-08-12T10:25:02",
      "lat": 12.943995,
      "lon": 77.607418
    },
    {
      "timestamp": "2023-08-12T10:25:18",
      "lat": 12.943988,
      "lon": 77.607091
    },
    {
      "timestamp": "2023-08-12T10:25:37",
      "lat": 12.943974,
      "lon": 77.606765
    },
    {
      "timestamp": "2023-08-12T10:26:01",
      "lat": 12.943957,
      "lon": 77.606439
    },
    {
      "timestamp": "2023-08-12T10:26:18",
      "lat": 12.943944,
      "lon": 77.606113
    },
    {
      "timestamp": "2023-08-12T10:26:35",
      "lat": 12.943985,
      "lon": 77.60579
    },
    {
      "timestamp": "2023-08-12T10:26:56",
      "lat": 12.944036,
      "lon": 77.605467
    },
    {
      "timestamp": "2023-08-12T10:27:19",
      "lat": 12.944088,
      "lon": 77.605145
    },
    {
      "timestamp": "2023-08-12T10:27:36",
      "lat": 12.94414,
      "lon": 77.604822
    },
    {
      "timestamp": "2023-08-12T10:28:01",
      "lat": 12.944192,
      "lon": 77.6045
    },
    {
      "timestamp": "2023-08-12T10:28:22",
      "lat": 12.944226,
      "lon": 77.604175
    },
    {
      "timestamp": "2023-08-12T10:28:40",
      "lat": 12.944254,
      "lon": 77.60385
    },
    {
      "timestamp": "2023-08-12T10:29:03",
      "lat": 12.944281,
      "lon": 77.603525
    },
    {
      "timestamp": "2023-08-12T10:29:19",
      "lat": 12.94431,
      "lon": 77.603199
    },
    {
      "timestamp": "2023-08-12T10:29:34",
      "lat": 12.944339,
      "lon": 77.602874
    },
    {
      "timestamp": "2023-08-12T10:29:51",
      "lat": 12.944109,
      "lon": 77.6028
    },
    {
      "timestamp": "2023-08-12T10:30:15",
      "lat": 12.943784,
      "lon": 77.602828
    },
    {
      "timestamp": "2023-08-12T10:30:38",
      "lat": 12.943457,
      "lon": 77.602845
    },
    {
      "timestamp": "2023-08-12T10:31:01",
      "lat": 12.943223,
      "lon": 77.602781
    },
    {
      "timestamp": "2023-08-12T10:31:21",
      "lat": 12.943329,
      "lon": 77.602472
    },
    {
      "timestamp": "2023-08-12T10:31:37",
      "lat": 12.943434,
      "lon": 77.602163
    },
    {
      "timestamp": "2023-08-12T10:31:52",
      "lat": 12.943134,
      "lon": 77.602055
    },
    {
      "timestamp": "2023-08-12T10:32:10",
      "lat": 12.943234,
      "lon": 77.601744
    },
    {
      "timestamp": "2023-08-12T10:32:25",
      "lat": 12.942966,
      "lon": 77.601619
    },
    {
      "timestamp": "2023-08-12T10:32:48",
      "lat": 12.943035,
      "lon": 77.601326
    },
    {
      "timestamp": "2023-08-12T10:33:09",
      "lat": 12.943235,
      "lon": 77.601077
    },
    {
      "timestamp": "2023-08-12T10:33:27",
      "lat": 12.943447,
      "lon": 77.600829
    },
    {
      "timestamp": "2023-08-12T10:33:51",
      "lat": 12.943575,
      "lon": 77.600539
    },
    {
      "timestamp": "2023-08-12T10:34:14",
      "lat": 12.943584,
      "lon": 77.600213
    },
    {
      "timestamp": "2023-08-12T10:34:30",
      "lat": 12.943818,
      "lon": 77.600122
    },
    {
      "timestamp": "2023-08-12T10:34:47",
      "lat": 12.943944,
      "lon": 77.599879
    },
    {
      "timestamp": "2023-08-12T10:35:11",
      "lat": 12.944011,
      "lon": 77.599559
    },
    {
      "timestamp": "2023-08-12T10:35:32",
      "lat": 12.943956,
      "lon": 77.59982
    },
    {
      "timestamp": "2023-08-12T10:35:52",
      "lat": 12.943877,
      "lon": 77.600125
    },
    {
      "timestamp": "2023-08-12T10:36:13",
      "lat": 12.943589,
      "lon": 77.600153
    },
    {
      "timestamp": "2023-08-12T10:36:34",
      "lat": 12.943578,
      "lon": 77.60048
    },
    {
      "timestamp": "2023-08-12T10:36:55",
      "lat": 12.943486,
      "lon": 77.600783
    },
    {
      "timestamp": "2023-08-12T10:37:15",
      "lat": 12.943273,
      "lon": 77.601031
    },
    {
      "timestamp": "2023-08-12T10:37:31",
      "lat": 12.943054,
      "lon": 77.601269
    },
    {
      "timestamp": "2023-08-12T10:37:55",
      "lat": 12.94295,
      "lon": 77.601579
    },
    {
      "timestamp": "2023-08-12T10:38:10",
      "lat": 12.943219,
      "lon": 77.601704
    },
    {
      "timestamp": "2023-08-12T10:38:29",
      "lat": 12.943153,
      "lon": 77.601998
    },
    {
      "timestamp": "2023-08-12T10:38:45",
      "lat": 12.943383,
      "lon": 77.602141
    },
    {
      "timestamp": "2023-08-12T10:39:08",
      "lat": 12.943348,
      "lon": 77.602415
    },
    {
      "timestamp": "2023-08-12T10:39:30",
      "lat": 12.943242,
      "lon": 77.602724
    },
    {
      "timestamp": "2023-08-12T10:39:50",
      "lat": 12.943398,
      "lon": 77.602846
    },
    {
      "timestamp": "2023-08-12T10:40:11",
      "lat": 12.943724,
      "lon": 77.602831
    },
    {
      "timestamp": "2023-08-12T10:40:31",
      "lat": 12.944049,
      "lon": 77.602806
    },
    {
      "timestamp": "2023-08-12T10:40:48",
      "lat": 12.944338,
      "lon": 77.602814
    },
    {
      "timestamp": "2023-08-12T10:41:13",
      "lat": 12.944315,
      "lon": 77.60314
    },
    {
      "timestamp": "2023-08-12T10:41:30",
      "lat": 12.944286,
      "lon": 77.603465
    },
    {
      "timestamp": "2023-08-12T10:41:45",
      "lat": 12.944259,
      "lon": 77.60379
    },
    {
      "timestamp": "2023-08-12T10:42:07",
      "lat": 12.944232,
      "lon": 77.604116
    },
    {
      "timestamp": "2023-08-12T10:42:23",
      "lat": 12.944202,
      "lon": 77.604441
    },
    {
      "timestamp": "2023-08-12T10:42:41",
      "lat": 12.94415,
      "lon": 77.604763
    },
    {
      "timestamp": "2023-08-12T10:43:00",
      "lat": 12.944097,
      "lon": 77.605086
    },
    {
      "timestamp": "2023-08-12T10:43:16",
      "lat": 12.944045,
      "lon": 77.605408
    },
    {
      "timestamp": "2023-08-12T10:43:34",
      "lat": 12.943994,
      "lon": 77.60573
    },
    {
      "timestamp": "2023-08-12T10:43:50",
      "lat": 12.943947,
      "lon": 77.606054
    },
    {
      "timestamp": "2023-08-12T10:44:12",
      "lat": 12.943953,
      "lon": 77.606379
    },
    {
      "timestamp": "2023-08-12T10:44:31",
      "lat": 12.943971,
      "lon": 77.606705
    },
    {
      "timestamp": "2023-08-12T10:44:50",
      "lat": 12.943987,
      "lon": 77.607032
    },
    {
      "timestamp": "2023-08-12T10:45:07",
      "lat": 12.943994,
      "lon": 77.607358
    },
    {
      "timestamp": "2023-08-12T10:45:30",
      "lat": 12.944001,
      "lon": 77.607684
    },
    {
      "timestamp": "2023-08-12T10:45:54",
      "lat": 12.944021,
      "lon": 77.608005
    },
    {
      "timestamp": "2023-08-12T10:46:12",
      "lat": 12.944004,
      "lon": 77.608331
    },
    {
      "timestamp": "2023-08-12T10:46:28",
      "lat": 12.94399,
      "lon": 77.608658
    },
    {
      "timestamp": "2023-08-12T10:46:48",
      "lat": 12.944106,
      "lon": 77.608856
    },
    {
      "timestamp": "2023-08-12T10:47:04",
      "lat": 12.944151,
      "lon": 77.609097
    },
    {
      "timestamp": "2023-08-12T10:47:24",
      "lat": 12.944112,
      "lon": 77.609421
    },
    {
      "timestamp": "2023-08-12T10:47:48",
      "lat": 12.944055,
      "lon": 77.609741
    },
    {
      "timestamp": "2023-08-12T10:48:08",
      "lat": 12.943979,
      "lon": 77.610058
    },
    {
      "timestamp": "2023-08-12T10:48:24",
      "lat": 12.943912,
      "lon": 77.610378
    },
    {
      "timestamp": "2023-08-12T10:48:41",
      "lat": 12.943787,
      "lon": 77.610676
    },
    {
      "timestamp": "2023-08-12T10:49:05",
      "lat": 12.943636,
      "lon": 77.610964
    },
    {
      "timestamp": "2023-08-12T10:49:25",
      "lat": 12.943542,
      "lon": 77.611276
    },
    {
      "timestamp": "2023-08-12T10:49:47",
      "lat": 12.943448,
      "lon": 77.611589
    },
    {
      "timestamp": "2023-08-12T10:50:04",
      "lat": 12.943408,
      "lon": 77.611912
    },
    {
      "timestamp": "2023-08-12T10:50:25",
      "lat": 12.943345,
      "lon": 77.612231
    },
    {
      "timestamp": "2023-08-12T10:50:42",
      "lat": 12.943257,
      "lon": 77.612546
    },
    {
      "timestamp": "2023-08-12T10:50:58",
      "lat": 12.943154,
      "lon": 77.612855
    },
    {
      "timestamp": "2023-08-12T10:51:23",
      "lat": 12.943017,
      "lon": 77.613148
    },
    {
      "timestamp": "2023-08-12T10:51:48",
      "lat": 12.942869,
      "lon": 77.613432
    },
    {
      "timestamp": "2023-08-12T10:52:05",
      "lat": 12.942764,
      "lon": 77.613741
    },
    {
      "timestamp": "2023-08-12T10:52:30",
      "lat": 12.942657,
      "lon": 77.614049
    },
    {
      "timestamp": "2023-08-12T10:52:55",
      "lat": 12.94252,
      "lon": 77.614345
    },
    {
      "timestamp": "2023-08-12T10:53:17",
      "lat": 12.942374,
      "lon": 77.614637
    },
    {
      "timestamp": "2023-08-12T10:53:42",
      "lat": 12.942231,
      "lon": 77.614931
    },
    {
      "timestamp": "2023-08-12T10:54:07",
      "lat": 12.942104,
      "lon": 77.615232
    },
    {
      "timestamp": "2023-08-12T10:54:32",
      "lat": 12.941945,
      "lon": 77.615517
    },
    {
      "timestamp": "2023-08-12T10:54:57",
      "lat": 12.941824,
      "lon": 77.615816
    },
    {
      "timestamp": "2023-08-12T10:55:15",
      "lat": 12.941776,
      "lon": 77.616138
    },
    {
      "timestamp": "2023-08-12T10:55:30",
      "lat": 12.941767,
      "lon": 77.616465
    },
    {
      "timestamp": "2023-08-12T10:55:48",
      "lat": 12.941752,
      "lon": 77.616791
    },
    {
      "timestamp": "2023-08-12T10:56:09",
      "lat": 12.941731,
      "lon": 77.617117
    },
    {
      "timestamp": "2023-08-12T10:56:31",
      "lat": 12.941796,
      "lon": 77.617368
    },
    {
      "timestamp": "2023-08-12T10:56:52",
      "lat": 12.942121,
      "lon": 77.617401
    },
    {
      "timestamp": "2023-08-12T10:57:14",
      "lat": 12.942164,
      "lon": 77.617662
    },
    {
      "timestamp": "2023-08-12T10:57:30",
      "lat": 12.942049,
      "lon": 77.617899
    },
    {
      "timestamp": "2023-08-12T10:57:46",
      "lat": 12.942079,
      "lon": 77.618224
    },
    {
      "timestamp": "2023-08-12T10:58:04",
      "lat": 12.942098,
      "lon": 77.61855
    },
    {
      "timestamp": "2023-08-12T10:58:20",
      "lat": 12.942271,
      "lon": 77.618708
    },
    {
      "timestamp": "2023-08-12T10:58:37",
      "lat": 12.942264,
      "lon": 77.619035
    },
    {
      "timestamp": "2023-08-12T10:58:57",
      "lat": 12.942258,
      "lon": 77.619361
    },
    {
      "timestamp": "2023-08-12T10:59:18",
      "lat": 12.942262,
      "lon": 77.619688
    },
    {
      "timestamp": "2023-08-12T10:59:41",
      "lat": 12.9421,
      "lon": 77.619887
    },
    {
      "timestamp": "2023-08-12T11:00:03",
      "lat": 12.941967,
      "lon": 77.620185
    },
    {
      "timestamp": "2023-08-12T11:00:26",
      "lat": 12.941819,
      "lon": 77.620476
    },
    {
      "timestamp": "2023-08-12T11:00:44",
      "lat": 12.941667,
      "lon": 77.620765
    },
    {
      "timestamp": "2023-08-12T11:01:04",
      "lat": 12.941515,
      "lon": 77.621054
    },
    {
      "timestamp": "2023-08-12T11:01:26",
      "lat": 12.941419,
      "lon": 77.621337
    },
    {
      "timestamp": "2023-08-12T11:01:41",
      "lat": 12.941615,
      "lon": 77.621598
    },
    {
      "timestamp": "2023-08-12T11:02:00",
      "lat": 12.941811,
      "lon": 77.621859
    },
    {
      "timestamp": "2023-08-12T11:02:25",
      "lat": 12.942009,
      "lon": 77.622119
    },
    {
      "timestamp": "2023-08-12T11:02:42",
      "lat": 12.942206,
      "lon": 77.622379
    },
    {
      "timestamp": "2023-08-12T11:03:02",
      "lat": 12.942401,
      "lon": 77.622641
    },
    {
      "timestamp": "2023-08-12T11:03:21",
      "lat": 12.942438,
      "lon": 77.622889
    },
    {
      "timestamp": "2023-08-12T11:03:41",
      "lat": 12.942221,
      "lon": 77.623133
    },
    {
      "timestamp": "2023-08-12T11:03:57",
      "lat": 12.941997,
      "lon": 77.62337
    },
    {
      "timestamp": "2023-08-12T11:04:21",
      "lat": 12.941772,
      "lon": 77.623608
    },
    {
      "timestamp": "2023-08-12T11:04:42",
      "lat": 12.941548,
      "lon": 77.623845
    },
    {
      "timestamp": "2023-08-12T11:05:03",
      "lat": 12.941323,
      "lon": 77.624082
    },
    {
      "timestamp": "2023-08-12T11:05:18",
      "lat": 12.941093,
      "lon": 77.624313
    },
    {
      "timestamp": "2023-08-12T11:05:39",
      "lat": 12.940863,
      "lon": 77.624545
    },
    {
      "timestamp": "2023-08-12T11:06:02",
      "lat": 12.940635,
      "lon": 77.624779
    },
    {
      "timestamp": "2023-08-12T11:06:20",
      "lat": 12.940401,
      "lon": 77.625007
    },
    {
      "timestamp": "2023-08-12T11:06:42",
      "lat": 12.940156,
      "lon": 77.625222
    },
    {
      "timestamp": "2023-08-12T11:07:02",
      "lat": 12.93991,
      "lon": 77.625426
    },
    {
      "timestamp": "2023-08-12T11:07:19",
      "lat": 12.940135,
      "lon": 77.625663
    },
    {
      "timestamp": "2023-08-12T11:07:35",
      "lat": 12.940351,
      "lon": 77.625905
    },
    {
      "timestamp": "2023-08-12T11:07:58",
      "lat": 12.940458,
      "lon": 77.626214
    },
    {
      "timestamp": "2023-08-12T11:08:16",
      "lat": 12.940552,
      "lon": 77.626527
    },
    {
      "timestamp": "2023-08-12T11:08:41",
      "lat": 12.94067,
      "lon": 77.626831
    },
    {
      "timestamp": "2023-08-12T11:08:58",
      "lat": 12.940792,
      "lon": 77.627133
    },
    {
      "timestamp": "2023-08-12T11:09:13",
      "lat": 12.940887,
      "lon": 77.627445
    },
    {
      "timestamp": "2023-08-12T11:09:30",
      "lat": 12.94087,
      "lon": 77.627685
    },
    {
      "timestamp": "2023-08-12T11:09:47",
      "lat": 12.940548,
      "lon": 77.627735
    },
    {
      "timestamp": "2023-08-12T11:10:10",
      "lat": 12.940358,
      "lon": 77.62789
    },
    {
      "timestamp": "2023-08-12T11:10:33",
      "lat": 12.940405,
      "lon": 77.628213
    },
    {
      "timestamp": "2023-08-12T11:10:48",
      "lat": 12.940228,
      "lon": 77.628372
    },
    {
      "timestamp": "2023-08-12T11:11:03",
      "lat": 12.940153,
      "lon": 77.628603
    },
    {
      "timestamp": "2023-08-12T11:11:23",
      "lat": 12.940171,
      "lon": 77.628928
    },
    {
      "timestamp": "2023-08-12T11:11:41",
      "lat": 12.940184,
      "lon": 77.629254
    },
    {
      "timestamp": "2023-08-12T11:12:04",
      "lat": 12.940171,
      "lon": 77.629555
    },
    {
      "timestamp": "2023-08-12T11:12:29",
      "lat": 12.939906,
      "lon": 77.629742
    },
    {
      "timestamp": "2023-08-12T11:12:51",
      "lat": 12.939667,
      "lon": 77.629962
    },
    {
      "timestamp": "2023-08-12T11:13:10",
      "lat": 12.939485,
      "lon": 77.629982
    },
    {
      "timestamp": "2023-08-12T11:13:31",
      "lat": 12.939159,
      "lon": 77.629982
    },
    {
      "timestamp": "2023-08-12T11:13:55",
      "lat": 12.938911,
      "lon": 77.629993
    },
    {
      "timestamp": "2023-08-12T11:14:17",
      "lat": 12.939225,
      "lon": 77.630083
    },
    {
      "timestamp": "2023-08-12T11:14:36",
      "lat": 12.939498,
      "lon": 77.63011
    },
    {
      "timestamp": "2023-08-12T11:14:56",
      "lat": 12.939743,
      "lon": 77.629905
    },
    {
      "timestamp": "2023-08-12T11:15:16",
      "lat": 12.939976,
      "lon": 77.629677
    },
    {
      "timestamp": "2023-08-12T11:15:32",
      "lat": 12.940259,
      "lon": 77.62952
    },
    {
      "timestamp": "2023-08-12T11:15:57",
      "lat": 12.940576,
      "lon": 77.62944
    },
    {
      "timestamp": "2023-08-12T11:16:16",
      "lat": 12.940887,
      "lon": 77.629344
    },
    {
      "timestamp": "2023-08-12T11:16:38",
      "lat": 12.941205,
      "lon": 77.62929
    },
    {
      "timestamp": "2023-08-12T11:17:03",
      "lat": 12.941531,
      "lon": 77.629284
    },
    {
      "timestamp": "2023-08-12T11:17:20",
      "lat": 12.941829,
      "lon": 77.629164
    },
    {
      "timestamp": "2023-08-12T11:17:39",
      "lat": 12.942136,
      "lon": 77.629053
    },
    {
      "timestamp": "2023-08-12T11:18:02",
      "lat": 12.942446,
      "lon": 77.628948
    },
    {
      "timestamp": "2023-08-12T11:18:26",
      "lat": 12.942738,
      "lon": 77.628813
    },
    {
      "timestamp": "2023-08-12T11:18:47",
      "lat": 12.942967,
      "lon": 77.62858
    },
    {
      "timestamp": "2023-08-12T11:19:05",
      "lat": 12.943222,
      "lon": 77.628434
    },
    {
      "timestamp": "2023-08-12T11:19:27",
      "lat": 12.943545,
      "lon": 77.628483
    },
    {
      "timestamp": "2023-08-12T11:19:45",
      "lat": 12.943869,
      "lon": 77.628523
    },
    {
      "timestamp": "2023-08-12T11:20:04",
      "lat": 12.944193,
      "lon": 77.628564
    },
    {
      "timestamp": "2023-08-12T11:20:22",
      "lat": 12.944505,
      "lon": 77.628611
    },
    {
      "timestamp": "2023-08-12T11:20:38",
      "lat": 12.944827,
      "lon": 77.62862
    },
    {
      "timestamp": "2023-08-12T11:20:55",
      "lat": 12.944875,
      "lon": 77.628899
    },
    {
      "timestamp": "2023-08-12T11:21:11",
      "lat": 12.945202,
      "lon": 77.62891
    },
    {
      "timestamp": "2023-08-12T11:21:36",
      "lat": 12.945528,
      "lon": 77.628922
    },
    {
      "timestamp": "2023-08-12T11:21:51",
      "lat": 12.945854,
      "lon": 77.628934
    },
    {
      "timestamp": "2023-08-12T11:22:15",
      "lat": 12.946181,
      "lon": 77.628948
    },
    {
      "timestamp": "2023-08-12T11:22:30",
      "lat": 12.946494,
      "lon": 77.628916
    },
    {
      "timestamp": "2023-08-12T11:22:55",
      "lat": 12.946757,
      "lon": 77.628724
    },
    {
      "timestamp": "2023-08-12T11:23:14",
      "lat": 12.947041,
      "lon": 77.628563
    },
    {
      "timestamp": "2023-08-12T11:23:36",
      "lat": 12.947325,
      "lon": 77.628401
    },
    {
      "timestamp": "2023-08-12T11:23:52",
      "lat": 12.947602,
      "lon": 77.628229
    },
    {
      "timestamp": "2023-08-12T11:24:08",
      "lat": 12.947889,
      "lon": 77.628073
    },
    {
      "timestamp": "2023-08-12T11:24:31",
      "lat": 12.948169,
      "lon": 77.627906
    },
    {
      "timestamp": "2023-08-12T11:24:47",
      "lat": 12.94845,
      "lon": 77.627739
    },
    {
      "timestamp": "2023-08-12T11:25:04",
      "lat": 12.948729,
      "lon": 77.627569
    },
    {
      "timestamp": "2023-08-12T11:25:22",
      "lat": 12.948997,
      "lon": 77.627385
    },
    {
      "timestamp": "2023-08-12T11:25:47",
      "lat": 12.949226,
      "lon": 77.627153
    },
    {
      "timestamp": "2023-08-12T11:26:09",
      "lat": 12.949442,
      "lon": 77.626908
    },
    {
      "timestamp": "2023-08-12T11:26:26",
      "lat": 12.94965,
      "lon": 77.626657
    },
    {
      "timestamp": "2023-08-12T11:26:46",
      "lat": 12.949858,
      "lon": 77.626408
    },
    {
      "timestamp": "2023-08-12T11:27:07",
      "lat": 12.950048,
      "lon": 77.626142
    },
    {
      "timestamp": "2023-08-12T11:27:26",
      "lat": 12.950221,
      "lon": 77.625866
    },
    {
      "timestamp": "2023-08-12T11:27:49",
      "lat": 12.950345,
      "lon": 77.625565
    },
    {
      "timestamp": "2023-08-12T11:28:09",
      "lat": 12.950417,
      "lon": 77.625247
    },
    {
      "timestamp": "2023-08-12T11:28:27",
      "lat": 12.950481,
      "lon": 77.624927
    },
    {
      "timestamp": "2023-08-12T11:28:43",
      "lat": 12.950546,
      "lon": 77.624607
    },
    {
      "timestamp": "2023-08-12T11:29:00",
      "lat": 12.95061,
      "lon": 77.624287
    },
    {
      "timestamp": "2023-08-12T11:29:20",
      "lat": 12.950677,
      "lon": 77.623967
    },
    {
      "timestamp": "2023-08-12T11:29:44",
      "lat": 12.95075,
      "lon": 77.623649
    },
    {
      "timestamp": "2023-08-12T11:30:06",
      "lat": 12.950824,
      "lon": 77.623331
    },
    {
      "timestamp": "2023-08-12T11:30:24",
      "lat": 12.950965,
      "lon": 77.623037
    },
    {
      "timestamp": "2023-08-12T11:30:40",
      "lat": 12.951107,
      "lon": 77.622743
    },
    {
      "timestamp": "2023-08-12T11:31:03",
      "lat": 12.951249,
      "lon": 77.622449
    },
    {
      "timestamp": "2023-08-12T11:31:23",
      "lat": 12.951398,
      "lon": 77.622158
    },
    {
      "timestamp": "2023-08-12T11:31:40",
      "lat": 12.951542,
      "lon": 77.621865
    },
    {
      "timestamp": "2023-08-12T11:32:01",
      "lat": 12.951691,
      "lon": 77.621575
    },
    {
      "timestamp": "2023-08-12T11:32:24",
      "lat": 12.951846,
      "lon": 77.621288
    },
    {
      "timestamp": "2023-08-12T11:32:48",
      "lat": 12.951999,
      "lon": 77.620999
    },
    {
      "timestamp": "2023-08-12T11:33:08",
      "lat": 12.952152,
      "lon": 77.620711
    },
    {
      "timestamp": "2023-08-12T11:33:32",
      "lat": 12.952305,
      "lon": 77.620423
    },
    {
      "timestamp": "2023-08-12T11:33:52",
      "lat": 12.952452,
      "lon": 77.620131
    },
    {
      "timestamp": "2023-08-12T11:34:09",
      "lat": 12.952588,
      "lon": 77.619834
    },
    {
      "timestamp": "2023-08-12T11:34:26",
      "lat": 12.952725,
      "lon": 77.619538
    },
    {
      "timestamp": "2023-08-12T11:34:49",
      "lat": 12.952864,
      "lon": 77.619242
    },
    {
      "timestamp": "2023-08-12T11:35:05",
      "lat": 12.953005,
      "lon": 77.618948
    },
    {
      "timestamp": "2023-08-12T11:35:25",
      "lat": 12.953144,
      "lon": 77.618652
    },
    {
      "timestamp": "2023-08-12T11:35:46",
      "lat": 12.953285,
      "lon": 77.618358
    },
    {
      "timestamp": "2023-08-12T11:36:10",
      "lat": 12.953424,
      "lon": 77.618063
    },
    {
      "timestamp": "2023-08-12T11:36:27",
      "lat": 12.953573,
      "lon": 77.617773
    },
    {
      "timestamp": "2023-08-12T11:36:45",
      "lat": 12.953718,
      "lon": 77.617481
    },
    {
      "timestamp": "2023-08-12T11:37:02",
      "lat": 12.953849,
      "lon": 77.617181
    },
    {
      "timestamp": "2023-08-12T11:37:22",
      "lat": 12.953976,
      "lon": 77.616881
    },
    {
      "timestamp": "2023-08-12T11:37:40",
      "lat": 12.954112,
      "lon": 77.616584
    },
    {
      "timestamp": "2023-08-12T11:37:55",
      "lat": 12.954243,
      "lon": 77.616285
    },
    {
      "timestamp": "2023-08-12T11:38:13",
      "lat": 12.954365,
      "lon": 77.615982
    },
    {
      "timestamp": "2023-08-12T11:38:36",
      "lat": 12.954492,
      "lon": 77.615681
    },
    {
      "timestamp": "2023-08-12T11:38:58",
      "lat": 12.954601,
      "lon": 77.615374
    },
    {
      "timestamp": "2023-08-12T11:39:15",
      "lat": 12.954711,
      "lon": 77.615066
    },
    {
      "timestamp": "2023-08-12T11:39:36",
      "lat": 12.95482,
      "lon": 77.614758
    },
    {
      "timestamp": "2023-08-12T11:39:58",
      "lat": 12.954939,
      "lon": 77.614454
    },
    {
      "timestamp": "2023-08-12T11:40:23",
      "lat": 12.95506,
      "lon": 77.614152
    },
    {
      "timestamp": "2023-08-12T11:40:42",
      "lat": 12.9552,
      "lon": 77.613858
    },
    {
      "timestamp": "2023-08-12T11:41:04",
      "lat": 12.955356,
      "lon": 77.613572
    },
    {
      "timestamp": "2023-08-12T11:41:19",
      "lat": 12.955501,
      "lon": 77.613279
    },
    {
      "timestamp": "2023-08-12T11:41:41",
      "lat": 12.955601,
      "lon": 77.612968
    },
    {
      "timestamp": "2023-08-12T11:42:06",
      "lat": 12.955702,
      "lon": 77.612658
    },
    {
      "timestamp": "2023-08-12T11:42:28",
      "lat": 12.955807,
      "lon": 77.612349
    },
    {
      "timestamp": "2023-08-12T11:42:44",
      "lat": 12.95591,
      "lon": 77.612039
    },
    {
      "timestamp": "2023-08-12T11:43:09",
      "lat": 12.956058,
      "lon": 77.611802
    },
    {
      "timestamp": "2023-08-12T11:43:26",
      "lat": 12.956382,
      "lon": 77.611841
    },
    {
      "timestamp": "2023-08-12T11:43:51",
      "lat": 12.956706,
      "lon": 77.611878
    },
    {
      "timestamp": "2023-08-12T11:44:09",
      "lat": 12.95703,
      "lon": 77.611919
    },
    {
      "timestamp": "2023-08-12T11:44:31",
      "lat": 12.957354,
      "lon": 77.61196
    },
    {
      "timestamp": "2023-08-12T11:44:46",
      "lat": 12.957678,
      "lon": 77.612001
    },
    {
      "timestamp": "2023-08-12T11:45:07",
      "lat": 12.958002,
      "lon": 77.612042
    },
    {
      "timestamp": "2023-08-12T11:45:25",
      "lat": 12.958326,
      "lon": 77.612082
    },
    {
      "timestamp": "2023-08-12T11:45:45",
      "lat": 12.95865,
      "lon": 77.612123
    },
    {
      "timestamp": "2023-08-12T11:46:01",
      "lat": 12.958895,
      "lon": 77.61207
    },
    {
      "timestamp": "2023-08-12T11:46:26",
      "lat": 12.958905,
      "lon": 77.611743
    },
    {
      "timestamp": "2023-08-12T11:46:51",
      "lat": 12.958915,
      "lon": 77.611417
    },
    {
      "timestamp": "2023-08-12T11:47:12",
      "lat": 12.958925,
      "lon": 77.61109
    },
    {
      "timestamp": "2023-08-12T11:47:33",
      "lat": 12.958804,
      "lon": 77.61082
    },
    {
      "timestamp": "2023-08-12T11:47:50",
      "lat": 12.958478,
      "lon": 77.610808
    },
    {
      "timestamp": "2023-08-12T11:48:07",
      "lat": 12.958524,
      "lon": 77.6105
    },
    {
      "timestamp": "2023-08-12T11:48:24",
      "lat": 12.958587,
      "lon": 77.61018
    },
    {
      "timestamp": "2023-08-12T11:48:44",
      "lat": 12.958649,
      "lon": 77.609859
    },
    {
      "timestamp": "2023-08-12T11:48:59",
      "lat": 12.958367,
      "lon": 77.609778
    },
    {
      "timestamp": "2023-08-12T11:49:24",
      "lat": 12.958045,
      "lon": 77.60973
    },
    {
      "timestamp": "2023-08-12T11:49:44",
      "lat": 12.957721,
      "lon": 77.609685
    },
    {
      "timestamp": "2023-08-12T11:50:03",
      "lat": 12.957398,
      "lon": 77.609637
    },
    {
      "timestamp": "2023-08-12T11:50:20",
      "lat": 12.957076,
      "lon": 77.609582
    },
    {
      "timestamp": "2023-08-12T11:50:45",
      "lat": 12.956754,
      "lon": 77.609527
    },
    {
      "timestamp": "2023-08-12T11:51:07",
      "lat": 12.956432,
      "lon": 77.609475
    },
    {
      "timestamp": "2023-08-12T11:51:32",
      "lat": 12.956108,
      "lon": 77.609436
    },
    {
      "timestamp": "2023-08-12T11:51:56",
      "lat": 12.955784,
      "lon": 77.609393
    },
    {
      "timestamp": "2023-08-12T11:52:15",
      "lat": 12.955461,
      "lon": 77.609348
    },
    {
      "timestamp": "2023-08-12T11:52:36",
      "lat": 12.955137,
      "lon": 77.609303
    },
    {
      "timestamp": "2023-08-12T11:52:56",
      "lat": 12.954951,
      "lon": 77.609154
    },
    {
      "timestamp": "2023-08-12T11:53:16",
      "lat": 12.954993,
      "lon": 77.60883
    },
    {
      "timestamp": "2023-08-12T11:53:38",
      "lat": 12.955036,
      "lon": 77.608506
    },
    {
      "timestamp": "2023-08-12T11:53:53",
      "lat": 12.955079,
      "lon": 77.608182
    },
    {
      "timestamp": "2023-08-12T11:54:09",
      "lat": 12.955123,
      "lon": 77.607859
    },
    {
      "timestamp": "2023-08-12T11:54:24",
      "lat": 12.955167,
      "lon": 77.607535
    },
    {
      "timestamp": "2023-08-12T11:54:44",
      "lat": 12.954917,
      "lon": 77.607426
    },
    {
      "timestamp": "2023-08-12T11:55:07",
      "lat": 12.954596,
      "lon": 77.607369
    },
    {
      "timestamp": "2023-08-12T11:55:29",
      "lat": 12.954274,
      "lon": 77.607311
    },
    {
      "timestamp": "2023-08-12T11:55:54",
      "lat": 12.953952,
      "lon": 77.607261
    },
    {
      "timestamp": "2023-08-12T11:56:14",
      "lat": 12.953686,
      "lon": 77.607334
    },
    {
      "timestamp": "2023-08-12T11:56:29",
      "lat": 12.953367,
      "lon": 77.607265
    },
    {
      "timestamp": "2023-08-12T11:56:52",
      "lat": 12.953048,
      "lon": 77.607192
    },
    {
      "timestamp": "2023-08-12T11:57:16",
      "lat": 12.952729,
      "lon": 77.607127
    },
    {
      "timestamp": "2023-08-12T11:57:34",
      "lat": 12.952406,
      "lon": 77.607174
    },
    {
      "timestamp": "2023-08-12T11:57:59",
      "lat": 12.952084,
      "lon": 77.607164
    },
    {
      "timestamp": "2023-08-12T11:58:17",
      "lat": 12.952274,
      "lon": 77.607194
    },
    {
      "timestamp": "2023-08-12T11:58:32",
      "lat": 12.952597,
      "lon": 77.607145
    },
    {
      "timestamp": "2023-08-12T11:58:53",
      "lat": 12.952919,
      "lon": 77.607162
    },
    {
      "timestamp": "2023-08-12T11:59:10",
      "lat": 12.953237,
      "lon": 77.607236
    },
    {
      "timestamp": "2023-08-12T11:59:31",
      "lat": 12.953556,
      "lon": 77.607306
    },
    {
      "timestamp": "2023-08-12T11:59:56",
      "lat": 12.953745,
      "lon": 77.60746
    },
    {
      "timestamp": "2023-08-12T12:00:11",
      "lat": 12.953676,
      "lon": 77.607779
    },
    {
      "timestamp": "2023-08-12T12:00:29",
      "lat": 12.953607,
      "lon": 77.608099
    },
    {
      "timestamp": "2023-08-12T12:00:46",
      "lat": 12.95354,
      "lon": 77.608418
    },
    {
      "timestamp": "2023-08-12T12:01:01",
      "lat": 12.953473,
      "lon": 77.608738
    },
    {
      "timestamp": "2023-08-12T12:01:26",
      "lat": 12.953398,
      "lon": 77.609056
    },
    {
      "timestamp": "2023-08-12T12:01:46",
      "lat": 12.953323,
      "lon": 77.609374
    },
    {
      "timestamp": "2023-08-12T12:02:02",
      "lat": 12.953504,
      "lon": 77.609583
    },
    {
      "timestamp": "2023-08-12T12:02:26",
      "lat": 12.953827,
      "lon": 77.60963
    },
    {
      "timestamp": "2023-08-12T12:02:41",
      "lat": 12.95415,
      "lon": 77.609678
    },
    {
      "timestamp": "2023-08-12T12:02:57",
      "lat": 12.954303,
      "lon": 77.609882
    },
    {
      "timestamp": "2023-08-12T12:03:14",
      "lat": 12.954352,
      "lon": 77.610203
    },
    {
      "timestamp": "2023-08-12T12:03:34",
      "lat": 12.954438,
      "lon": 77.610518
    },
    {
      "timestamp": "2023-08-12T12:03:49",
      "lat": 12.954372,
      "lon": 77.610832
    },
    {
      "timestamp": "2023-08-12T12:04:07",
      "lat": 12.954285,
      "lon": 77.611147
    },
    {
      "timestamp": "2023-08-12T12:04:27",
      "lat": 12.954183,
      "lon": 77.611457
    },
    {
      "timestamp": "2023-08-12T12:04:47",
      "lat": 12.953957,
      "lon": 77.611537
    },
    {
      "timestamp": "2023-08-12T12:05:02",
      "lat": 12.95378,
      "lon": 77.611696
    }
  ]
}