{
  "vehicle_id": "SE1_KA04AB5794_JETTING",
  "date": "2023-12-19",
  "points": [
    {
      "timestamp": "2023-12-19T09:20:00",
      "lat": 12.953277,
      "lon": 77.611805
    },
    {
      "timestamp": "2023-12-19T09:20:17",
      "lat": 12.953379,
      "lon": 77.611491
    },
    {
      "timestamp": "2023-12-19T09:20:41",
      "lat": 12.953598,
      "lon": 77.611413
    },
    {
      "timestamp": "2023-12-19T09:21:01",
      "lat": 12.95391,
      "lon": 77.611521
    },
    {
      "timestamp": "2023-12-19T09:21:22",
      "lat": 12.954164,
      "lon": 77.611501
    },
    {
      "timestamp": "2023-12-19T09:21:43",
      "lat": 12.954273,
      "lon": 77.61119
    },
    {
      "timestamp": "2023-12-19T09:21:59",
      "lat": 12.954361,
      "lon": 77.610873
    },
    {
      "timestamp": "2023-12-19T09:22:20",
      "lat": 12.954451,
      "lon": 77.610558
    },
    {
      "timestamp": "2023-12-19T09:22:45",
      "lat": 12.95477,
      "lon": 77.61064
    },
    {
      "timestamp": "2023-12-19T09:23:02",
      "lat": 12.955089,
      "lon": 77.610722
    },
    {
      "timestamp": "2023-12-19T09:23:27",
      "lat": 12.955408,
      "lon": 77.610805
    },
    {
      "timestamp": "2023-12-19T09:23:50",
      "lat": 12.955733,
      "lon": 77.610834
    },
    {
      "timestamp": "2023-12-19T09:24:09",
      "lat": 12.956063,
      "lon": 77.610831
    },
    {
      "timestamp": "2023-12-19T09:24:31",
      "lat": 12.956392,
      "lon": 77.610828
    },
    {
      "timestamp": "2023-12-19T09:24:56",
      "lat": 12.956722,
      "lon": 77.610825
    },
    {
      "timestamp": "2023-12-19T09:25:12",
      "lat": 12.957051,
      "lon": 77.610822
    },
    {
      "timestamp": "2023-12-19T09:25:35",
      "lat": 12.957381,
      "lon": 77.610818
    },
    {
      "timestamp": "2023-12-19T09:25:52",
      "lat": 12.95771,
      "lon": 77.610815
    },
    {
      "timestamp": "2023-12-19T09:26:11",
      "lat": 12.958039,
      "lon": 77.610812
    },
    {
      "timestamp": "2023-12-19T09:26:28",
      "lat": 12.958369,
      "lon": 77.610809
    },
    {
      "timestamp": "2023-12-19T09:26:48",
      "lat": 12.958698,
      "lon": 77.610816
    },
    {
      "timestamp": "2023-12-19T09:27:11",
      "lat": 12.958928,
      "lon": 77.610987
    },
    {
      "timestamp": "2023-12-19T09:27:33",
      "lat": 12.958918,
      "lon": 77.611316
    },
    {
      "timestamp": "2023-12-19T09:27:55",
      "lat": 12.958908,
      "lon": 77.611646
    },
    {
      "timestamp": "2023-12-19T09:28:16",
      "lat": 12.958898,
      "lon": 77.611975
    },
    {
      "timestamp": "2023-12-19T09:28:39",
      "lat": 12.958742,
      "lon": 77.612134
    },
    {
      "timestamp": "2023-12-19T09:28:59",
      "lat": 12.958415,
      "lon": 77.612094
    },
    {
      "timestamp": "2023-12-19T09:29:18",
      "lat": 12.958088,
      "lon": 77.612052
    },
    {
      "timestamp": "2023-12-19T09:29:34",
      "lat": 12.957761,
      "lon": 77.612011
    },
    {
      "timestamp": "2023-12-19T09:29:55",
      "lat": 12.957434,
      "lon": 77.61197
    },
    {
      "timestamp": "2023-12-19T09:30:15",
      "lat": 12.957107,
      "lon": 77.611929
    },
    {
      "timestamp": "2023-12-19T09:30:30",
      "lat": 12.95678,
      "lon": 77.611888
    },
    {
      "timestamp": "2023-12-19T09:30:51",
      "lat": 12.956453,
      "lon": 77.611848
    },
    {
      "timestamp": "2023-12-19T09:31:09",
      "lat": 12.956126,
      "lon": 77.611812
    },
    {
      "timestamp": "2023-12-19T09:31:30",
      "lat": 12.955931,
      "lon": 77.611977
    },
    {
      "timestamp": "2023-12-19T09:31:52",
      "lat": 12.955827,
      "lon": 77.612289
    },
    {
      "timestamp": "2023-12-19T09:32:08",
      "lat": 12.955722,
      "lon": 77.612602
    },
    {
      "timestamp": "2023-12-19T09:32:30",
      "lat": 12.955617,
      "lon": 77.612914
    },
    {
      "timestamp": "2023-12-19T09:32:53",
      "lat": 12.955521,
      "lon": 77.613229
    },
    {
      "timestamp": "2023-12-19T09:33:15",
      "lat": 12.955382,
      "lon": 77.613527
    },
    {
      "timestamp": "2023-12-19T09:33:36",
      "lat": 12.955222,
      "lon": 77.613815
    },
    {
      "timestamp": "2023-12-19T09:33:54",
      "lat": 12.955072,
      "lon": 77.614108
    },
    {
      "timestamp": "2023-12-19T09:34:09",
      "lat": 12.954956,
      "lon": 77.614415
    },
    {
      "timestamp": "2023-12-19T09:34:25",
      "lat": 12.954833,
      "lon": 77.614721
    },
    {
      "timestamp": "2023-12-19T09:34:45",
      "lat": 12.954723,
      "lon": 77.615031
    },
    {
      "timestamp": "2023-12-19T09:35:04",
      "lat": 12.954613,
      "lon": 77.615342
    },
    {
      "timestamp": "2023-12-19T09:35:29",
      "lat": 12.954503,
      "lon": 77.615652
    },
    {
      "timestamp": "2023-12-19T09:35:52",
      "lat": 12.954376,
      "lon": 77.615956
    },
    {
      "timestamp": "2023-12-19T09:36:11",
      "lat": 12.954252,
      "lon": 77.616261
    },
    {
      "timestamp": "2023-12-19T09:36:33",
      "lat": 12.954121,
      "lon": 77.616563
    },
    {
      "timestamp": "2023-12-19T09:36:54",
      "lat": 12.953983,
      "lon": 77.616863
    },
    {
      "timestamp": "2023-12-19T09:37:16",
      "lat": 12.953855,
      "lon": 77.617166
    },
    {
      "timestamp": "2023-12-19T09:37:36",
      "lat": 12.953724,
      "lon": 77.617468
    },
    {
      "timestamp": "2023-12-19T09:38:01",
      "lat": 12.953578,
      "lon": 77.617763
    },
    {
      "timestamp": "2023-12-19T09:38:23",
      "lat": 12.953428,
      "lon": 77.618055
    },
    {
      "timestamp": "2023-12-19T09:38:42",
      "lat": 12.953287,
      "lon": 77.618353
    },
    {
      "timestamp": "2023-12-19T09:38:59",
      "lat": 12.953144,
      "lon": 77.61865
    },
    {
      "timestamp": "2023-12-19T09:39:22",
      "lat": 12.953005,
      "lon": 77.618949
    },
    {
      "timestamp": "2023-12-19T09:39:47",
      "lat": 12.952862,
      "lon": 77.619245
    },
    {
      "timestamp": "2023-12-19T09:40:10",
      "lat": 12.952722,
      "lon": 77.619544
    },
    {
      "timestamp": "2023-12-19T09:40:25",
      "lat": 12.952584,
      "lon": 77.619843
    },
    {
      "timestamp": "2023-12-19T09:40:44",
      "lat": 12.952447,
      "lon": 77.620142
    },
    {
      "timestamp": "2023-12-19T09:41:00",
      "lat": 12.952298,
      "lon": 77.620436
    },
    {
      "timestamp": "2023-12-19T09:41:17",
      "lat": 12.952143,
      "lon": 77.620727
    },
    {
      "timestamp": "2023-12-19T09:41:36",
      "lat": 12.951989,
      "lon": 77.621018
    },
    {
      "timestamp": "2023-12-19T09:41:53",
      "lat": 12.951834,
      "lon": 77.621309
    },
    {
      "timestamp": "2023-12-19T09:42:10",
      "lat": 12.951676,
      "lon": 77.621597
    },
    {
      "timestamp": "2023-12-19T09:42:31",
      "lat": 12.951529,
      "lon": 77.621892
    },
    {
      "timestamp": "2023-12-19T09:42:46",
      "lat": 12.951383,
      "lon": 77.622187
    },
    {
      "timestamp": "2023-12-19T09:43:01",
      "lat": 12.951234,
      "lon": 77.62248
    },
    {
      "timestamp": "2023-12-19T09:43:26",
      "lat": 12.95109,
      "lon": 77.622777
    },
    {
      "timestamp": "2023-12-19T09:43:41",
      "lat": 12.950947,
      "lon": 77.623074
    },
    {
      "timestamp": "2023-12-19T09:44:02",
      "lat": 12.950814,
      "lon": 77.623374
    },
    {
      "timestamp": "2023-12-19T09:44:26",
      "lat": 12.950738,
      "lon": 77.623694
    },
    {
      "timestamp": "2023-12-19T09:44:51",
      "lat": 12.950667,
      "lon": 77.624016
    },
    {
      "timestamp": "2023-12-19T09:45:08",
      "lat": 12.9506,
      "lon": 77.624339
    },
    {
      "timestamp": "2023-12-19T09:45:29",
      "lat": 12.950535,
      "lon": 77.624662
    },
    {
      "timestamp": "2023-12-19T09:45:50",
      "lat": 12.95047,
      "lon": 77.624984
    },
    {
      "timestamp": "2023-12-19T09:46:10",
      "lat": 12.950405,
      "lon": 77.625307
    },
    {
      "timestamp": "2023-12-19T09:46:26",
      "lat": 12.950326,
      "lon": 77.625627
    },
    {
      "timestamp": "2023-12-19T09:46:50",
      "lat": 12.950188,
      "lon": 77.625924
    },
    {
      "timestamp": "2023-12-19T09:47:15",
      "lat": 12.950008,
      "lon": 77.626199
    },
    {
      "timestamp": "2023-12-19T09:47:32",
      "lat": 12.949812,
      "lon": 77.626464
    },
    {
      "timestamp": "2023-12-19T09:47:57",
      "lat": 12.949599,
      "lon": 77.626712
    },
    {
      "timestamp": "2023-12-19T09:48:21",
      "lat": 12.949391,
      "lon": 77.626967
    },
    {
      "timestamp": "2023-12-19T09:48:46",
      "lat": 12.949172,
      "lon": 77.627214
    },
    {
      "timestamp": "2023-12-19T09:49:11",
      "lat": 12.948935,
      "lon": 77.627442
    },
    {
      "timestamp": "2023-12-19T09:49:32",
      "lat": 12.948655,
      "lon": 77.627615
    },
    {
      "timestamp": "2023-12-19T09:49:53",
      "lat": 12.948373,
      "lon": 77.627785
    },
    {
      "timestamp": "2023-12-19T09:50:12",
      "lat": 12.948089,
      "lon": 77.627954
    },
    {
      "timestamp": "2023-12-19T09:50:31",
      "lat": 12.947804,
      "lon": 77.628118
    },
    {
      "timestamp": "2023-12-19T09:50:54",
      "lat": 12.94752,
      "lon": 77.628284
    },
    {
      "timestamp": "2023-12-19T09:51:15",
      "lat": 12.947236,
      "lon": 77.628451
    },
    {
      "timestamp": "2023-12-19T09:51:35",
      "lat": 12.94695,
      "lon": 77.628614
    },
    {
      "timestamp": "2023-12-19T09:51:51",
      "lat": 12.946669,
      "lon": 77.628785
    },
    {
      "timestamp": "2023-12-19T09:52:12",
      "lat": 12.946396,
      "lon": 77.628959
    },
    {
      "timestamp": "2023-12-19T09:52:30",
      "lat": 12.946067,
      "lon": 77.628942
    },
    {
      "timestamp": "2023-12-19T09:52:53",
      "lat": 12.945738,
      "lon": 77.628931
    },
    {
      "timestamp": "2023-12-19T09:53:10",
      "lat": 12.945409,
      "lon": 77.628917
    },
    {
      "timestamp": "2023-12-19T09:53:32",
      "lat": 12.94508,
      "lon": 77.628907
    },
    {
      "timestamp": "2023-12-19T09:53:48",
      "lat": 12.944825,
      "lon": 77.628822
    },
    {
      "timestamp": "2023-12-19T09:54:13",
      "lat": 12.944703,
      "lon": 77.628613
    },
    {
      "timestamp": "2023-12-19T09:54:31",
      "lat": 12.944386,
      "lon": 77.628596
    },
    {
      "timestamp": "2023-12-19T09:54:49",
      "lat": 12.944061,
      "lon": 77.628545
    },
    {
      "timestamp": "2023-12-19T09:55:04",
      "lat": 12.943733,
      "lon": 77.628507
    },
    {
      "timestamp": "2023-12-19T09:55:24",
      "lat": 12.943407,
      "lon": 77.628463
    },
    {
      "timestamp": "2023-12-19T09:55:43",
      "lat": 12.943094,
      "lon": 77.628447
    },
    {
      "timestamp": "2023-12-19T09:56:03",
      "lat": 12.942865,
      "lon": 77.628684
    },
    {
      "timestamp": "2023-12-19T09:56:26",
      "lat": 12.942615,
      "lon": 77.628891
    },
    {
      "timestamp": "2023-12-19T09:56:50",
      "lat": 12.942302,
      "lon": 77.628995
    },
    {
      "timestamp": "2023-12-19T09:57:11",
      "lat": 12.941992,
      "lon": 77.629105
    },
    {
      "timestamp": "2023-12-19T09:57:35",
      "lat": 12.941681,
      "lon": 77.629213
    },
    {
      "timestamp": "2023-12-19T09:57:59",
      "lat": 12.941371,
      "lon": 77.629279
    },
    {
      "timestamp": "2023-12-19T09:58:20",
      "lat": 12.941043,
      "lon": 77.629301
    },
    {
      "timestamp": "2023-12-19T09:58:41",
      "lat": 12.940733,
      "lon": 77.629403
    },
    {
      "timestamp": "2023-12-19T09:59:03",
      "lat": 12.940412,
      "lon": 77.629479
    },
    {
      "timestamp": "2023-12-19T09:59:21",
      "lat": 12.940103,
      "lon": 77.629589
    },
    {
      "timestamp": "2023-12-19T09:59:44",
      "lat": 12.939853,
      "lon": 77.6298
    },
    {
      "timestamp": "2023-12-19T10:00:02",
      "lat": 12.939601,
      "lon": 77.630011
    },
    {
      "timestamp": "2023-12-19T10:00:18",
      "lat": 12.9394,
      "lon": 77.629982
    },
    {
      "timestamp": "2023-12-19T10:00:42",
      "lat": 12.939071,
      "lon": 77.629982
    },
    {
      "timestamp": "2023-12-19T10:01:01",
      "lat": 12.938998,
      "lon": 77.630018
    },
    {
      "timestamp": "2023-12-19T10:01:26",
      "lat": 12.939315,
      "lon": 77.630108
    },
    {
      "timestamp": "2023-12-19T10:01:44",
      "lat": 12.939559,
      "lon": 77.630043
    },
    {
      "timestamp": "2023-12-19T10:02:01",
      "lat": 12.939818,
      "lon": 77.62984
    },
    {
      "timestamp": "2023-12-19T10:02:23",
      "lat": 12.940058,
      "lon": 77.629617
    },
    {
      "timestamp": "2023-12-19T10:02:47",
      "lat": 12.940196,
      "lon": 77.62938
    },
    {
      "timestamp": "2023-12-19T10:03:04",
      "lat": 12.940173,
      "lon": 77.629052
    },
    {
      "timestamp": "2023-12-19T10:03:26",
      "lat": 12.940168,
      "lon": 77.628722
    },
    {
      "timestamp": "2023-12-19T10:03:46",
      "lat": 12.94012,
      "lon": 77.628397
    },
    {
      "timestamp": "2023-12-19T10:04:01",
      "lat": 12.940422,
      "lon": 77.628326
    },
    {
      "timestamp": "2023-12-19T10:04:20",
      "lat": 12.940374,
      "lon": 77.628001
    },
    {
      "timestamp": "2023-12-19T10:04:45",
      "lat": 12.94044,
      "lon": 77.627756
    },
    {
      "timestamp": "2023-12-19T10:05:07",
      "lat": 12.940765,
      "lon": 77.627699
    },
    {
      "timestamp": "2023-12-19T10:05:30",
      "lat": 12.940918,
      "lon": 77.627544
    },
    {
      "timestamp": "2023-12-19T10:05:48",
      "lat": 12.940821,
      "lon": 77.627229
    },
    {
      "timestamp": "2023-12-19T10:06:05",
      "lat": 12.940713,
      "lon": 77.626918
    },
    {
      "timestamp": "2023-12-19T10:06:25",
      "lat": 12.940584,
      "lon": 77.626616
    },
    {
      "timestamp": "2023-12-19T10:06:44",
      "lat": 12.940484,
      "lon": 77.626302
    },
    {
      "timestamp": "2023-12-19T10:07:01",
      "lat": 12.940382,
      "lon": 77.625989
    },
    {
      "timestamp": "2023-12-19T10:07:16",
      "lat": 12.940194,
      "lon": 77.625725
    },
    {
      "timestamp": "2023-12-19T10:07:38",
      "lat": 12.939967,
      "lon": 77.625486
    },
    {
      "timestamp": "2023-12-19T10:07:54",
      "lat": 12.939734,
      "lon": 77.625253
    },
    {
      "timestamp": "2023-12-19T10:08:12",
      "lat": 12.939688,
      "lon": 77.625021
    },
    {
      "timestamp": "2023-12-19T10:08:36",
      "lat": 12.93992,
      "lon": 77.624787
    },
    {
      "timestamp": "2023-12-19T10:08:58",
      "lat": 12.940152,
      "lon": 77.624553
    },
    {
      "timestamp": "2023-12-19T10:09:14",
      "lat": 12.940384,
      "lon": 77.624319
    },
    {
      "timestamp": "2023-12-19T10:09:34",
      "lat": 12.940317,
      "lon": 77.624069
    },
    {
      "timestamp": "2023-12-19T10:09:55",
      "lat": 12.940112,
      "lon": 77.62381
    },
    {
      "timestamp": "2023-12-19T10:10:11",
      "lat": 12.939908,
      "lon": 77.623552
    },
    {
      "timestamp": "2023-12-19T10:10:33",
      "lat": 12.939704,
      "lon": 77.623293
    },
    {
      "timestamp": "2023-12-19T10:10:52",
      "lat": 12.9395,
      "lon": 77.623035
    },
    {
      "timestamp": "2023-12-19T10:11:08",
      "lat": 12.939569,
      "lon": 77.622799
    },
    {
      "timestamp": "2023-12-19T10:11:24",
      "lat": 12.939405,
      "lon": 77.622556
    },
    {
      "timestamp": "2023-12-19T10:11:41",
      "lat": 12.939651,
      "lon": 77.622337
    },
    {
      "timestamp": "2023-12-19T10:12:00",
      "lat": 12.939524,
      "lon": 77.622103
    },
    {
      "timestamp": "2023-12-19T10:12:16",
      "lat": 12.939296,
      "lon": 77.621865
    },
    {
      "timestamp": "2023-12-19T10:12:36",
      "lat": 12.939167,
      "lon": 77.62164
    },
    {
      "timestamp": "2023-12-19T10:13:01",
      "lat": 12.939394,
      "lon": 77.621402
    },
    {
      "timestamp": "2023-12-19T10:13:17",
      "lat": 12.939612,
      "lon": 77.621155
    },
    {
      "timestamp": "2023-12-19T10:13:34",
      "lat": 12.939843,
      "lon": 77.620922
    },
    {
      "timestamp": "2023-12-19T10:13:49",
      "lat": 12.94009,
      "lon": 77.620704
    },
    {
      "timestamp": "2023-12-19T10:14:12",
      "lat": 12.940326,
      "lon": 77.620473
    },
    {
      "timestamp": "2023-12-19T10:14:33",
      "lat": 12.940516,
      "lon": 77.62021
    },
    {
      "timestamp": "2023-12-19T10:14:48",
      "lat": 12.94067,
      "lon": 77.619919
    },
    {
      "timestamp": "2023-12-19T10:15:05",
      "lat": 12.940826,
      "lon": 77.619629
    },
    {
      "timestamp": "2023-12-19T10:15:26",
      "lat": 12.940776,
      "lon": 77.61939
    },
    {
      "timestamp": "2023-12-19T10:15:45",
      "lat": 12.940582,
      "lon": 77.619186
    },
    {
      "timestamp": "2023-12-19T10:16:04",
      "lat": 12.940727,
      "lon": 77.618889
    },
    {
      "timestamp": "2023-12-19T10:16:27",
      "lat": 12.940871,
      "lon": 77.618593
    },
    {
      "timestamp": "2023-12-19T10:16:51",
      "lat": 12.940985,
      "lon": 77.618286
    },
    {
      "timestamp": "2023-12-19T10:17:16",
      "lat": 12.941062,
      "lon": 77.617966
    },
    {
      "timestamp": "2023-12-19T10:17:32",
      "lat": 12.941087,
      "lon": 77.617638
    },
    {
      "timestamp": "2023-12-19T10:17:47",
      "lat": 12.941088,
      "lon": 77.617315
    },
    {
      "timestamp": "2023-12-19T10:18:05",
      "lat": 12.941382,
      "lon": 77.617301
    },
    {
      "timestamp": "2023-12-19T10:18:27",
      "lat": 12.941408,
      "lon": 77.616973
    },
    {
      "timestamp": "2023-12-19T10:18:45",
      "lat": 12.941434,
      "lon": 77.616645
    },
    {
      "timestamp": "2023-12-19T10:19:05",
      "lat": 12.94146,
      "lon": 77.616316
    },
    {
      "timestamp": "2023-12-19T10:19:25",
      "lat": 12.941695,
      "lon": 77.616201
    },
    {
      "timestamp": "2023-12-19T10:19:42",
      "lat": 12.941795,
      "lon": 77.615948
    },
    {
      "timestamp": "2023-12-19T10:20:03",
      "lat": 12.94188,
      "lon": 77.615632
    },
    {
      "timestamp": "2023-12-19T10:20:19",
      "lat": 12.942041,
      "lon": 77.615344
    },
    {
      "timestamp": "2023-12-19T10:20:41",
      "lat": 12.942182,
      "lon": 77.615047
    },
    {
      "timestamp": "2023-12-19T10:20:59",
      "lat": 12.942319,
      "lon": 77.614748
    },
    {
      "timestamp": "2023-12-19T10:21:22",
      "lat": 12.942466,
      "lon": 77.614453
    },
    {
      "timestamp": "2023-12-19T10:21:37",
      "lat": 12.942608,
      "lon": 77.614156
    },
    {
      "timestamp": "2023-12-19T10:21:53",
      "lat": 12.94273,
      "lon": 77.613851
    },
    {
      "timestamp": "2023-12-19T10:22:14",
      "lat": 12.942831,
      "lon": 77.613537
    },
    {
      "timestamp": "2023-12-19T10:22:38",
      "lat": 12.942943,
      "lon": 77.613227
    },
    {
      "timestamp": "2023-12-19T10:22:55",
      "lat": 12.943116,
      "lon": 77.612954
    },
    {
      "timestamp": "2023-12-19T10:23:17",
      "lat": 12.943226,
      "lon": 77.612644
    },
    {
      "timestamp": "2023-12-19T10:23:41",
      "lat": 12.943318,
      "lon": 77.612328
    },
    {
      "timestamp": "2023-12-19T10:24:00",
      "lat": 12.943399,
      "lon": 77.612009
    },
    {
      "timestamp": "2023-12-19T10:24:21",
      "lat": 12.943428,
      "lon": 77.611681
    },
    {
      "timestamp": "2023-12-19T10:24:41",
      "lat": 12.943516,
      "lon": 77.611364
    },
    {
      "timestamp": "2023-12-19T10:24:58",
      "lat": 12.943611,
      "lon": 77.611048
    },
    {
      "timestamp": "2023-12-19T10:25:22",
      "lat": 12.943744,
      "lon": 77.61075
    },
    {
      "timestamp": "2023-12-19T10:25:47",
      "lat": 12.943894,
      "lon": 77.610459
    },
    {
      "timestamp": "2023-12-19T10:26:07",
      "lat": 12.943961,
      "lon": 77.610136
    },
    {
      "timestamp": "2023-12-19T10:26:31",
      "lat": 12.944037,
      "lon": 77.609816
    },
    {
      "timestamp": "2023-12-19T10:26:48",
      "lat": 12.944114,
      "lon": 77.609495
    },
    {
      "timestamp": "2023-12-19T10:27:08",
      "lat": 12.944142,
      "lon": 77.609168
    },
    {
      "timestamp": "2023-12-19T10:27:23",
      "lat": 12.944174,
      "lon": 77.608852
    },
    {
      "timestamp": "2023-12-19T10:27:46",
      "lat": 12.943988,
      "lon": 77.608723
    },
    {
      "timestamp": "2023-12-19T10:28:04",
      "lat": 12.944001,
      "lon": 77.608394
    },
    {
      "timestamp": "2023-12-19T10:28:21",
      "lat": 12.944018,
      "lon": 77.608065
    },
    {
      "timestamp": "2023-12-19T10:28:45",
      "lat": 12.944003,
      "lon": 77.607741
    },
    {
      "timestamp": "2023-12-19T10:29:03",
      "lat": 12.943995,
      "lon": 77.607412
    },
    {
      "timestamp": "2023-12-19T10:29:27",
      "lat": 12.943988,
      "lon": 77.607083
    },
    {
      "timestamp": "2023-12-19T10:29:43",
      "lat": 12.943973,
      "lon": 77.606754
    },
    {
      "timestamp": "2023-12-19T10:30:04",
      "lat": 12.943956,
      "lon": 77.606425
    },
    {
      "timestamp": "2023-12-19T10:30:23",
      "lat": 12.943945,
      "lon": 77.606096
    },
    {
      "timestamp": "2023-12-19T10:30:40",
      "lat": 12.943988,
      "lon": 77.605769
    },
    {
      "timestamp": "2023-12-19T10:30:59",
      "lat": 12.94404,
      "lon": 77.605444
    },
    {
      "timestamp": "2023-12-19T10:31:19",
      "lat": 12.944092,
      "lon": 77.605119
    },
    {
      "timestamp": "2023-12-19T10:31:42",
      "lat": 12.944145,
      "lon": 77.604794
    },
    {
      "timestamp": "2023-12-19T10:32:04",
      "lat": 12.944197,
      "lon": 77.604468
    },
    {
      "timestamp": "2023-12-19T10:32:24",
      "lat": 12.944229,
      "lon": 77.604141
    },
    {
      "timestamp": "2023-12-19T10:32:48",
      "lat": 12.944257,
      "lon": 77.603812
    },
    {
      "timestamp": "2023-12-19T10:33:09",
      "lat": 12.944285,
      "lon": 77.603484
    },
    {
      "timestamp": "2023-12-19T10:33:25",
      "lat": 12.944314,
      "lon": 77.603156
    },
    {
      "timestamp": "2023-12-19T10:33:42",
      "lat": 12.944339,
      "lon": 77.602828
    },
    {
      "timestamp": "2023-12-19T10:33:57",
      "lat": 12.94406,
      "lon": 77.602805
    },
    {
      "timestamp": "2023-12-19T10:34:15",
      "lat": 12.943731,
      "lon": 77.602831
    },
    {
      "timestamp": "2023-12-19T10:34:40",
      "lat": 12.943402,
      "lon": 77.602846
    },
    {
      "timestamp": "2023-12-19T10:35:02",
      "lat": 12.943241,
      "lon": 77.602726
    },
    {
      "timestamp": "2023-12-19T10:35:21",
      "lat": 12.943348,
      "lon": 77.602414
    },
    {
      "timestamp": "2023-12-19T10:35:45",
      "lat": 12.94338,
      "lon": 77.60214
    },
    {
      "timestamp": "2023-12-19T10:36:04",
      "lat": 12.943155,
      "lon": 77.601992
    },
    {
      "timestamp": "2023-12-19T10:36:29",
      "lat": 12.94321,
      "lon": 77.601701
    },
    {
      "timestamp": "2023-12-19T10:36:44",
      "lat": 12.942954,
      "lon": 77.601567
    },
    {
      "timestamp": "2023-12-19T10:37:04",
      "lat": 12.943059,
      "lon": 77.601255
    },
    {
      "timestamp": "2023-12-19T10:37:27",
      "lat": 12.943285,
      "lon": 77.601017
    },
    {
      "timestamp": "2023-12-19T10:37:44",
      "lat": 12.943499,
      "lon": 77.600767
    },
    {
      "timestamp": "2023-12-19T10:38:04",
      "lat": 12.943579,
      "lon": 77.600456
    },
    {
      "timestamp": "2023-12-19T10:38:28",
      "lat": 12.943591,
      "lon": 77.600127
    },
    {
      "timestamp": "2023-12-19T10:38:45",
      "lat": 12.943895,
      "lon": 77.600111
    },
    {
      "timestamp": "2023-12-19T10:39:05",
      "lat": 12.943963,
      "lon": 77.599788
    },
    {
      "timestamp": "2023-12-19T10:39:20",
      "lat": 12.944081,
      "lon": 77.599544
    },
    {
      "timestamp": "2023-12-19T10:39:44",
      "lat": 12.944398,
      "lon": 77.599632
    },
    {
      "timestamp": "2023-12-19T10:40:02",
      "lat": 12.944708,
      "lon": 77.599742
    },
    {
      "timestamp": "2023-12-19T10:40:18",
      "lat": 12.945018,
      "lon": 77.599855
    },
    {
      "timestamp": "2023-12-19T10:40:41",
      "lat": 12.945324,
      "lon": 77.599977
    },
    {
      "timestamp": "2023-12-19T10:41:04",
      "lat": 12.945629,
      "lon": 77.600101
    },
    {
      "timestamp": "2023-12-19T10:41:27",
      "lat": 12.945935,
      "lon": 77.600222
    },
    {
      "timestamp": "2023-12-19T10:41:50",
      "lat": 12.946245,
      "lon": 77.600334
    },
    {
      "timestamp": "2023-12-19T10:42:08",
      "lat": 12.946551,
      "lon": 77.600457
    },
    {
      "timestamp": "2023-12-19T10:42:24",
      "lat": 12.946859,
      "lon": 77.600573
    },
    {
      "timestamp": "2023-12-19T10:42:39",
      "lat": 12.947173,
      "lon": 77.600673
    },
    {
      "timestamp": "2023-12-19T10:43:00",
      "lat": 12.947487,
      "lon": 77.600773
    },
    {
      "timestamp": "2023-12-19T10:43:24",
      "lat": 12.947709,
      "lon": 77.600917
    },
    {
      "timestamp": "2023-12-19T10:43:40",
      "lat": 12.947593,
      "lon": 77.601225
    },
    {
      "timestamp": "2023-12-19T10:44:03",
      "lat": 12.94767,
      "lon": 77.601442
    },
    {
      "timestamp": "2023-12-19T10:44:21",
      "lat": 12.947972,
      "lon": 77.601571
    },
    {
      "timestamp": "2023-12-19T10:44:42",
      "lat": 12.948277,
      "lon": 77.601693
    },
    {
      "timestamp": "2023-12-19T10:45:06",
      "lat": 12.948472,
      "lon": 77.601918
    },
    {
      "timestamp": "2023-12-19T10:45:30",
      "lat": 12.948508,
      "lon": 77.602242
    },
    {
      "timestamp": "2023-12-19T10:45:53",
      "lat": 12.948407,
      "lon": 77.602554
    },
    {
      "timestamp": "2023-12-19T10:46:16",
      "lat": 12.948648,
      "lon": 77.602705
    },
    {
      "timestamp": "2023-12-19T10:46:36",
      "lat": 12.948952,
      "lon": 77.602833
    },
    {
      "timestamp": "2023-12-19T10:46:54",
      "lat": 12.949256,
      "lon": 77.60296
    },
    {
      "timestamp": "2023-12-19T10:47:17",
      "lat": 12.949566,
      "lon": 77.603072
    },
    {
      "timestamp": "2023-12-19T10:47:35",
      "lat": 12.949871,
      "lon": 77.603195
    },
    {
      "timestamp": "2023-12-19T10:47:54",
      "lat": 12.950173,
      "lon": 77.603326
    },
    {
      "timestamp": "2023-12-19T10:48:09",
      "lat": 12.950488,
      "lon": 77.603419
    },
    {
      "timestamp": "2023-12-19T10:48:26",
      "lat": 12.950807,
      "lon": 77.603501
    },
    {
      "timestamp": "2023-12-19T10:48:44",
      "lat": 12.951118,
      "lon": 77.603609
    },
    {
      "timestamp": "2023-12-19T10:49:06",
      "lat": 12.951408,
      "lon": 77.603765
    },
    {
      "timestamp": "2023-12-19T10:49:30",
      "lat": 12.951697,
      "lon": 77.603924
    },
    {
      "timestamp": "2023-12-19T10:49:50",
      "lat": 12.951985,
      "lon": 77.604083
    },
    {
      "timestamp": "2023-12-19T10:50:07",
      "lat": 12.952249,
      "lon": 77.604272
    },
    {
      "timestamp": "2023-12-19T10:50:32",
      "lat": 12.952401,
      "lon": 77.604564
    },
    {
      "timestamp": "2023-12-19T10:50:50",
      "lat": 12.952557,
      "lon": 77.604854
    },
    {
      "timestamp": "2023-12-19T10:51:08",
      "lat": 12.952712,
      "lon": 77.605145
    },
    {
      "timestamp": "2023-12-19T10:51:32",
      "lat": 12.952578,
      "lon": 77.605245
    },
    {
      "timestamp": "2023-12-19T10:51:47",
      "lat": 12.95225,
      "lon": 77.605217
    },
    {
      "timestamp": "2023-12-19T10:52:02",
      "lat": 12.951936,
      "lon": 77.605206
    },
    {
      "timestamp": "2023-12-19T10:52:25",
      "lat": 12.951875,
      "lon": 77.605529
    },
    {
      "timestamp": "2023-12-19T10:52:50",
      "lat": 12.951814,
      "lon": 77.605853
    },
    {
      "timestamp": "2023-12-19T10:53:08",
      "lat": 12.951753,
      "lon": 77.606177
    },
    {
      "timestamp": "2023-12-19T10:53:32",
      "lat": 12.951697,
      "lon": 77.606501
    },
    {
      "timestamp": "2023-12-19T10:53:57",
      "lat": 12.951638,
      "lon": 77.606826
    },
    {
      "timestamp": "2023-12-19T10:54:22",
      "lat": 12.951582,
      "lon": 77.60715
    },
    {
      "timestamp": "2023-12-19T10:54:39",
      "lat": 12.951513,
      "lon": 77.607472
    },
    {
      "timestamp": "2023-12-19T10:54:54",
      "lat": 12.951579,
      "lon": 77.607784
    },
    {
      "timestamp": "2023-12-19T10:55:13",
      "lat": 12.951808,
      "lon": 77.608017
    },
    {
      "timestamp": "2023-12-19T10:55:32",
      "lat": 12.951909,
      "lon": 77.608319
    },
    {
      "timestamp": "2023-12-19T10:55:54",
      "lat": 12.95194,
      "lon": 77.608647
    },
    {
      "timestamp": "2023-12-19T10:56:15",
      "lat": 12.951891,
      "lon": 77.608971
    },
    {
      "timestamp": "2023-12-19T10:56:31",
      "lat": 12.951835,
      "lon": 77.609296
    },
    {
      "timestamp": "2023-12-19T10:56:46",
      "lat": 12.951779,
      "lon": 77.60962
    },
    {
      "timestamp": "2023-12-19T10:57:07",
      "lat": 12.951718,
      "lon": 77.609944
    },
    {
      "timestamp": "2023-12-19T10:57:27",
      "lat": 12.951657,
      "lon": 77.610267
    },
    {
      "timestamp": "2023-12-19T10:57:49",
      "lat": 12.951635,
      "lon": 77.610595
    },
    {
      "timestamp": "2023-12-19T10:58:10",
      "lat": 12.951614,
      "lon": 77.610924
    },
    {
      "timestamp": "2023-12-19T10:58:34",
      "lat": 12.951597,
      "lon": 77.611253
    },
    {
      "timestamp": "2023-12-19T10:58:53",
      "lat": 12.951743,
      "lon": 77.611498
    },
    {
      "timestamp": "2023-12-19T10:59:10",
      "lat": 12.951973,
      "lon": 77.611715
    },
    {
      "timestamp": "2023-12-19T10:59:25",
      "lat": 12.951932,
      "lon": 77.611879
    },
    {
      "timestamp": "2023-12-19T10:59:47",
      "lat": 12.951842,
      "lon": 77.612194
    },
    {
      "timestamp": "2023-12-19T11:00:07",
      "lat": 12.951785,
      "lon": 77.612518
    },
    {
      "timestamp": "2023-12-19T11:00:31",
      "lat": 12.951872,
      "lon": 77.612755
    },
    {
      "timestamp": "2023-12-19T11:00:52",
      "lat": 12.951836,
      "lon": 77.613043
    },
    {
      "timestamp": "2023-12-19T11:01:11",
      "lat": 12.951747,
      "lon": 77.61336
    },
    {
      "timestamp": "2023-12-19T11:01:27",
      "lat": 12.951655,
      "lon": 77.613676
    },
    {
      "timestamp": "2023-12-19T11:01:49",
      "lat": 12.95156,
      "lon": 77.613992
    },
    {
      "timestamp": "2023-12-19T11:02:05",
      "lat": 12.951861,
      "lon": 77.614123
    },
    {
      "timestamp": "2023-12-19T11:02:24",
      "lat": 12.951907,
      "lon": 77.614359
    },
    {
      "timestamp": "2023-12-19T11:02:44",
      "lat": 12.951778,
      "lon": 77.614662
    },
    {
      "timestamp": "2023-12-19T11:03:09",
      "lat": 12.951617,
      "lon": 77.614933
    },
    {
      "timestamp": "2023-12-19T11:03:32",
      "lat": 12.951828,
      "lon": 77.61518
    },
    {
      "timestamp": "2023-12-19T11:03:50",
      "lat": 12.952043,
      "lon": 77.615422
    },
    {
      "timestamp": "2023-12-19T11:04:10",
      "lat": 12.9523,
      "lon": 77.615627
    },
    {
      "timestamp": "2023-12-19T11:04:29",
      "lat": 12.952544,
      "lon": 77.615787
    },
    {
      "timestamp": "2023-12-19T11:04:45",
      "lat": 12.952676,
      "lon": 77.615975
    },
    {
      "timestamp": "2023-12-19T11:05:06",
      "lat": 12.952624,
      "lon": 77.6163
    },
    {
      "timestamp": "2023-12-19T11:05:30",
      "lat": 12.95287,
      "lon": 77.616406
    },
    {
      "timestamp": "2023-12-19T11:05:55",
      "lat": 12.95292,
      "lon": 77.616672
    },
    {
      "timestamp": "2023-12-19T11:06:16",
      "lat": 12.953246,
      "lon": 77.616719
    },
    {
      "timestamp": "2023-12-19T11:06:32",
      "lat": 12.953506,
      "lon": 77.616819
    },
    {
      "timestamp": "2023-12-19T11:06:51",
      "lat": 12.953485,
      "lon": 77.617148
    },
    {
      "timestamp": "2023-12-19T11:07:14",
      "lat": 12.953631,
      "lon": 77.617341
    },
    {
      "timestamp": "2023-12-19T11:07:37",
      "lat": 12.953694,
      "lon": 77.617532
    },
    {
      "timestamp": "2023-12-19T11:07:57",
      "lat": 12.953608,
      "lon": 77.617803
    },
    {
      "timestamp": "2023-12-19T11:08:14",
      "lat": 12.953915,
      "lon": 77.61792
    },
    {
      "timestamp": "2023-12-19T11:08:38",
      "lat": 12.95424,
      "lon": 77.617957
    },
    {
      "timestamp": "2023-12-19T11:09:00",
      "lat": 12.954559,
      "lon": 77.618027
    },
    {
      "timestamp": "2023-12-19T11:09:24",
      "lat": 12.95479,
      "lon": 77.61826
    },
    {
      "timestamp": "2023-12-19T11:09:48",
      "lat": 12.955024,
      "lon": 77.618491
    },
    {
      "timestamp": "2023-12-19T11:10:09",
      "lat": 12.955314,
      "lon": 77.618641
    },
    {
      "timestamp": "2023-12-19T11:10:34",
      "lat": 12.955602,
      "lon": 77.618802
    },
    {
      "timestamp": "2023-12-19T11:10:51",
      "lat": 12.955714,
      "lon": 77.619045
    },
    {
      "timestamp": "2023-12-19T11:11:12",
      "lat": 12.955765,
      "lon": 77.619369
    },
    {
      "timestamp": "2023-12-19T11:11:32",
      "lat": 12.955992,
      "lon": 77.619494
    },
    {
      "timestamp": "2023-12-19T11:11:54",
      "lat": 12.956066,
      "lon": 77.619814
    },
    {
      "timestamp": "2023-12-19T11:12:09",
      "lat": 12.956099,
      "lon": 77.620141
    },
    {
      "timestamp": "2023-12-19T11:12:33",
      "lat": 12.956059,
      "lon": 77.620437
    },
    {
      "timestamp": "2023-12-19T11:12:51",
      "lat": 12.955846,
      "lon": 77.62057
    },
    {
      "timestamp": "2023-12-19T11:13:14",
      "lat": 12.955915,
      "lon": 77.620893
    },
    {
      "timestamp": "2023-12-19T11:13:34",
      "lat": 12.956136,
      "lon": 77.621035
    },
    {
      "timestamp": "2023-12-19T11:13:50",
      "lat": 12.956224,
      "lon": 77.621333
    },
    {
      "timestamp": "2023-12-19T11:14:13",
      "lat": 12.956371,
      "lon": 77.621628
    },
    {
      "timestamp": "2023-12-19T11:14:31",
      "lat": 12.9565,
      "lon": 77.621931
    },
    {
      "timestamp": "2023-12-19T11:14:52",
      "lat": 12.956665,
      "lon": 77.622137
    },
    {
      "timestamp": "2023-12-19T11:15:10",
      "lat": 12.956793,
      "lon": 77.62244
    },
    {
      "timestamp": "2023-12-19T11:15:33",
      "lat": 12.957092,
      "lon": 77.622303
    },
    {
      "timestamp": "2023-12-19T11:15:54",
      "lat": 12.95739,
      "lon": 77.622165
    },
    {
      "timestamp": "2023-12-19T11:16:18",
      "lat": 12.957692,
      "lon": 77.622033
    },
    {
      "timestamp": "2023-12-19T11:16:37",
      "lat": 12.957842,
      "lon": 77.622273
    },
    {
      "timestamp": "2023-12-19T11:16:57",
      "lat": 12.957965,
      "lon": 77.622579
    },
    {
      "timestamp": "2023-12-19T11:17:21",
      "lat": 12.958087,
      "lon": 77.622884
    },
    {
      "timestamp": "2023-12-19T11:17:36",
      "lat": 12.95821,
      "lon": 77.62319
    },
    {
      "timestamp": "2023-12-19T11:17:54",
      "lat": 12.958333,
      "lon": 77.623496
    },
    {
      "timestamp": "2023-12-19T11:18:16",
      "lat": 12.958455,
      "lon": 77.623802
    },
    {
      "timestamp": "2023-12-19T11:18:32",
      "lat": 12.958358,
      "lon": 77.623559
    },
    {
      "timestamp": "2023-12-19T11:18:50",
      "lat": 12.958235,
      "lon": 77.623254
    },
    {
      "timestamp": "2023-12-19T11:19:13",
      "lat": 12.958113,
      "lon": 77.622948
    },
    {
      "timestamp": "2023-12-19T11:19:34",
      "lat": 12.95799,
      "lon": 77.622642
    },
    {
      "timestamp": "2023-12-19T11:19:49",
      "lat": 12.957868,
      "lon": 77.622336
    },
    {
      "timestamp": "2023-12-19T11:20:11",
      "lat": 12.957745,
      "lon": 77.62203
    },
    {
      "timestamp": "2023-12-19T11:20:27",
      "lat": 12.957453,
      "lon": 77.622137
    },
    {
      "timestamp": "2023-12-19T11:20:49",
      "lat": 12.957153,
      "lon": 77.622274
    },
    {
      "timestamp": "2023-12-19T11:21:05",
      "lat": 12.956855,
      "lon": 77.622413
    },
    {
      "timestamp": "2023-12-19T11:21:27",
      "lat": 12.956691,
      "lon": 77.6222
    },
    {
      "timestamp": "2023-12-19T11:21:43",
      "lat": 12.956524,
      "lon": 77.621994
    },
    {
      "timestamp": "2023-12-19T11:21:58",
      "lat": 12.956398,
      "lon": 77.62169
    },
    {
      "timestamp": "2023-12-19T11:22:23",
      "lat": 12.956255,
      "lon": 77.621393
    },
    {
      "timestamp": "2023-12-19T11:22:47",
      "lat": 12.956168,
      "lon": 77.62108
    },
    {
      "timestamp": "2023-12-19T11:23:12",
      "lat": 12.95588,
      "lon": 77.620981
    },
    {
      "timestamp": "2023-12-19T11:23:31",
      "lat": 12.955557,
      "lon": 77.62092
    },
    {
      "timestamp": "2023-12-19T11:23:50",
      "lat": 12.955238,
      "lon": 77.620848
    },
    {
      "timestamp": "2023-12-19T11:24:13",
      "lat": 12.954918,
      "lon": 77.620771
    },
    {
      "timestamp": "2023-12-19T11:24:38",
      "lat": 12.954598,
      "lon": 77.620693
    },
    {
      "timestamp": "2023-12-19T11:24:59",
      "lat": 12.954285,
      "lon": 77.620592
    },
    {
      "timestamp": "2023-12-19T11:25:22",
      "lat": 12.953968,
      "lon": 77.6205
    },
    {
      "timestamp": "2023-12-19T11:25:44",
      "lat": 12.953651,
      "lon": 77.620413
    },
    {
      "timestamp": "2023-12-19T11:26:06",
      "lat": 12.95333,
      "lon": 77.620338
    },
    {
      "timestamp": "2023-12-19T11:26:26",
      "lat": 12.953009,
      "lon": 77.620264
    },
    {
      "timestamp": "2023-12-19T11:26:46",
      "lat": 12.952684,
      "lon": 77.620209
    },
    {
      "timestamp": "2023-12-19T11:27:05",
      "lat": 12.95239,
      "lon": 77.620263
    },
    {
      "timestamp": "2023-12-19T11:27:21",
      "lat": 12.952235,
      "lon": 77.620554
    },
    {
      "timestamp": "2023-12-19T11:27:36",
      "lat": 12.952081,
      "lon": 77.620845
    },
    {
      "timestamp": "2023-12-19T11:27:59",
      "lat": 12.951926,
      "lon": 77.621136
    },
    {
      "timestamp": "2023-12-19T11:28:17",
      "lat": 12.951773,
      "lon": 77.621427
    },
    {
      "timestamp": "2023-12-19T11:28:40",
      "lat": 12.951487,
      "lon": 77.621371
    },
    {
      "timestamp": "2023-12-19T11:29:04",
      "lat": 12.951177,
      "lon": 77.621257
    },
    {
      "timestamp": "2023-12-19T11:29:25",
      "lat": 12.950869,
      "lon": 77.621141
    },
    {
      "timestamp": "2023-12-19T11:29:47",
      "lat": 12.950568,
      "lon": 77.621009
    },
    {
      "timestamp": "2023-12-19T11:30:12",
      "lat": 12.950276,
      "lon": 77.620856
    },
    {
      "timestamp": "2023-12-19T11:30:33",
      "lat": 12.949988,
      "lon": 77.620696
    },
    {
      "timestamp": "2023-12-19T11:30:48",
      "lat": 12.949699,
      "lon": 77.620537
    },
    {
      "timestamp": "2023-12-19T11:31:13",
      "lat": 12.949412,
      "lon": 77.620377
    },
    {
      "timestamp": "2023-12-19T11:31:35",
      "lat": 12.949126,
      "lon": 77.620214
    },
    {
      "timestamp": "2023-12-19T11:31:52",
      "lat": 12.948837,
      "lon": 77.620056
    },
    {
      "timestamp": "2023-12-19T11:32:07",
      "lat": 12.948549,
      "lon": 77.619895
    },
    {
      "timestamp": "2023-12-19T11:32:32",
      "lat": 12.948261,
      "lon": 77.619735
    },
    {
      "timestamp": "2023-12-19T11:32:56",
      "lat": 12.947974,
      "lon": 77.619574
    },
    {
      "timestamp": "2023-12-19T11:33:13",
      "lat": 12.947686,
      "lon": 77.619413
    },
    {
      "timestamp": "2023-12-19T11:33:28",
      "lat": 12.947395,
      "lon": 77.619259
    },
    {
      "timestamp": "2023-12-19T11:33:48",
      "lat": 12.947106,
      "lon": 77.619102
    },
    {
      "timestamp": "2023-12-19T11:34:05",
      "lat": 12.946816,
      "lon": 77.618946
    },
    {
      "timestamp": "2023-12-19T11:34:21",
      "lat": 12.946526,
      "lon": 77.618788
    },
    {
      "timestamp": "2023-12-19T11:34:44",
      "lat": 12.946231,
      "lon": 77.618645
    },
    {
      "timestamp": "2023-12-19T11:35:04",
      "lat": 12.94591,
      "lon": 77.618585
    },
    {
      "timestamp": "2023-12-19T11:35:22",
      "lat": 12.945668,
      "lon": 77.618792
    },
    {
      "timestamp": "2023-12-19T11:35:38",
      "lat": 12.945462,
      "lon": 77.619049
    },
    {
      "timestamp": "2023-12-19T11:35:54",
      "lat": 12.945222,
      "lon": 77.619186
    },
    {
      "timestamp": "2023-12-19T11:36:18",
      "lat": 12.944908,
      "lon": 77.619087
    },
    {
      "timestamp": "2023-12-19T11:36:35",
      "lat": 12.94459,
      "lon": 77.618999
    },
    {
      "timestamp": "2023-12-19T11:36:54",
      "lat": 12.944271,
      "lon": 77.618919
    },
    {
      "timestamp": "2023-12-19T11:37:09",
      "lat": 12.943953,
      "lon": 77.618833
    },
    {
      "timestamp": "2023-12-19T11:37:31",
      "lat": 12.944267,
      "lon": 77.618914
    },
    {
      "timestamp": "2023-12-19T11:37:46",
      "lat": 12.944586,
      "lon": 77.618997
    },
    {
      "timestamp": "2023-12-19T11:38:11",
      "lat": 12.944903,
      "lon": 77.619086
    },
    {
      "timestamp": "2023-12-19T11:38:29",
      "lat": 12.945218,
      "lon": 77.619185
    },
    {
      "timestamp": "2023-12-19T11:38:45",
      "lat": 12.945459,
      "lon": 77.619052
    },
    {
      "timestamp": "2023-12-19T11:39:08",
      "lat": 12.945665,
      "lon": 77.618795
    },
    {
      "timestamp": "2023-12-19T11:39:25",
      "lat": 12.945906,
      "lon": 77.618585
    },
    {
      "timestamp": "2023-12-19T11:39:47",
      "lat": 12.946115,
      "lon": 77.618404
    },
    {
      "timestamp": "2023-12-19T11:40:09",
      "lat": 12.946377,
      "lon": 77.618357
    },
    {
      "timestamp": "2023-12-19T11:40:26",
      "lat": 12.94669,
      "lon": 77.618458
    },
    {
      "timestamp": "2023-12-19T11:40:48",
      "lat": 12.946929,
      "lon": 77.618376
    },
    {
      "timestamp": "2023-12-19T11:41:12",
      "lat": 12.947137,
      "lon": 77.618212
    },
    {
      "timestamp": "2023-12-19T11:41:31",
      "lat": 12.947454,
      "lon": 77.618302
    },
    {
      "timestamp": "2023-12-19T11:41:54",
      "lat": 12.947743,
      "lon": 77.618329
    },
    {
      "timestamp": "2023-12-19T11:42:19",
      "lat": 12.9479,
      "lon": 77.61804
    },
    {
      "timestamp": "2023-12-19T11:42:36",
      "lat": 12.948062,
      "lon": 77.617753
    },
    {
      "timestamp": "2023-12-19T11:43:01",
      "lat": 12.948222,
      "lon": 77.617465
    },
    {
      "timestamp": "2023-12-19T11:43:25",
      "lat": 12.948382,
      "lon": 77.617177
    },
    {
      "timestamp": "2023-12-19T11:43:43",
      "lat": 12.948591,
      "lon": 77.617022
    },
    {
      "timestamp": "2023-12-19T11:44:08",
      "lat": 12.948898,
      "lon": 77.617142
    },
    {
      "timestamp": "2023-12-19T11:44:32",
      "lat": 12.949176,
      "lon": 77.617314
    },
    {
      "timestamp": "2023-12-19T11:44:53",
      "lat": 12.949464,
      "lon": 77.617475
    },
    {
      "timestamp": "2023-12-19T11:45:12",
      "lat": 12.949751,
      "lon": 77.617636
    },
    {
      "timestamp": "2023-12-19T11:45:28",
      "lat": 12.950039,
      "lon": 77.617798
    },
    {
      "timestamp": "2023-12-19T11:45:52",
      "lat": 12.950323,
      "lon": 77.617961
    },
    {
      "timestamp": "2023-12-19T11:46:17",
      "lat": 12.950594,
      "lon": 77.618149
    },
    {
      "timestamp": "2023-12-19T11:46:32",
      "lat": 12.950867,
      "lon": 77.618332
    },
    {
      "timestamp": "2023-12-19T11:46:49",
      "lat": 12.951141,
      "lon": 77.618516
    },
    {
      "timestamp": "2023-12-19T11:47:08",
      "lat": 12.951414,
      "lon": 77.618699
    },
    {
      "timestamp": "2023-12-19T11:47:26",
      "lat": 12.951648,
      "lon": 77.618931
    },
    {
      "timestamp": "2023-12-19T11:47:48",
      "lat": 12.951955,
      "lon": 77.618823
    },
    {
      "timestamp": "2023-12-19T11:48:11",
      "lat": 12.952272,
      "lon": 77.618848
    },
    {
      "timestamp": "2023-12-19T11:48:26",
      "lat": 12.952308,
      "lon": 77.618641
    },
    {
      "timestamp": "2023-12-19T11:48:49",
      "lat": 12.952488,
      "lon": 77.618365
    },
    {
      "timestamp": "2023-12-19T11:49:05",
      "lat": 12.952672,
      "lon": 77.618092
    },
    {
      "timestamp": "2023-12-19T11:49:25",
      "lat": 12.952897,
      "lon": 77.617864
    },
    {
      "timestamp": "2023-12-19T11:49:47",
      "lat": 12.953219,
      "lon": 77.617806
    },
    {
      "timestamp": "2023-12-19T11:50:07",
      "lat": 12.953546,
      "lon": 77.617809
    },
    {
      "timestamp": "2023-12-19T11:50:22",
      "lat": 12.9537,
      "lon": 77.617519
    },
    {
      "timestamp": "2023-12-19T11:50:47",
      "lat": 12.953833,
      "lon": 77.617218
    },
    {
      "timestamp": "2023-12-19T11:51:02",
      "lat": 12.953961,
      "lon": 77.616915
    },
    {
      "timestamp": "2023-12-19T11:51:19",
      "lat": 12.954097,
      "lon": 77.616615
    },
    {
      "timestamp": "2023-12-19T11:51:40",
      "lat": 12.954232,
      "lon": 77.616314
    },
    {
      "timestamp": "2023-12-19T11:52:01",
      "lat": 12.954355,
      "lon": 77.616008
    },
    {
      "timestamp": "2023-12-19T11:52:26",
      "lat": 12.954483,
      "lon": 77.615705
    },
    {
      "timestamp": "2023-12-19T11:52:43",
      "lat": 12.954594,
      "lon": 77.615395
    },
    {
      "timestamp": "2023-12-19T11:52:59",
      "lat": 12.954704,
      "lon": 77.615084
    },
    {
      "timestamp": "2023-12-19T11:53:17",
      "lat": 12.954814,
      "lon": 77.614774
    },
    {
      "timestamp": "2023-12-19T11:53:35",
      "lat": 12.954933,
      "lon": 77.614467
    },
    {
      "timestamp": "2023-12-19T11:53:53",
      "lat": 12.955057,
      "lon": 77.614162
    },
    {
      "timestamp": "2023-12-19T11:54:08",
      "lat": 12.955196,
      "lon": 77.613865
    },
    {
      "timestamp": "2023-12-19T11:54:31",
      "lat": 12.955354,
      "lon": 77.613576
    },
    {
      "timestamp": "2023-12-19T11:54:53",
      "lat": 12.9555,
      "lon": 77.613281
    },
    {
      "timestamp": "2023-12-19T11:55:15",
      "lat": 12.955601,
      "lon": 77.612968
    },
    {
      "timestamp": "2023-12-19T11:55:38",
      "lat": 12.955704,
      "lon": 77.612655
    },
    {
      "timestamp": "2023-12-19T11:56:03",
      "lat": 12.955809,
      "lon": 77.612343
    },
    {
      "timestamp": "2023-12-19T11:56:27",
      "lat": 12.955913,
      "lon": 77.61203
    },
    {
      "timestamp": "2023-12-19T11:56:46",
      "lat": 12.95607,
      "lon": 77.611803
    },
    {
      "timestamp": "2023-12-19T11:57:02",
      "lat": 12.956397,
      "lon": 77.611843
    },
    {
      "timestamp": "2023-12-19T11:57:19",
      "lat": 12.956724,
      "lon": 77.611881
    },
    {
      "timestamp": "2023-12-19T11:57:37",
      "lat": 12.957051,
      "lon": 77.611922
    },
    {
      "timestamp": "2023-12-19T11:58:02",
      "lat": 12.957378,
      "lon": 77.611963
    },
    {
      "timestamp": "2023-12-19T11:58:21",
      "lat": 12.957705,
      "lon": 77.612004
    },
    {
      "timestamp": "2023-12-19T11:58:38",
      "lat": 12.958032,
      "lon": 77.612045
    },
    {
      "timestamp": "2023-12-19T11:58:54",
      "lat": 12.958359,
      "lon": 77.612087
    },
    {
      "timestamp": "2023-12-19T11:59:17",
      "lat": 12.958686,
      "lon": 77.612127
    },
    {
      "timestamp": "2023-12-19T11:59:41",
      "lat": 12.958896,
      "lon": 77.612031
    },
    {
      "timestamp": "2023-12-19T12:00:05",
      "lat": 12.958906,
      "lon": 77.611702
    },
    {
      "timestamp": "2023-12-19T12:00:27",
      "lat": 12.958916,
      "lon": 77.611373
    },
    {
      "timestamp": "2023-12-19T12:00:49",
      "lat": 12.958926,
      "lon": 77.611044
    },
    {
      "timestamp": "2023-12-19T12:01:13",
      "lat": 12.958755,
      "lon": 77.610818
    },
    {
      "timestamp": "2023-12-19T12:01:35",
      "lat": 12.958425,
      "lon": 77.610808
    },
    {
      "timestamp": "2023-12-19T12:01:55",
      "lat": 12.958096,
      "lon": 77.610811
    },
    {
      "timestamp": "2023-12-19T12:02:19",
      "lat": 12.957766,
      "lon": 77.610815
    },
    {
      "timestamp": "2023-12-19T12:02:43",
      "lat": 12.957437,
      "lon": 77.610818
    },
    {
      "timestamp": "2023-12-19T12:03:01",
      "lat": 12.957108,
      "lon": 77.610821
    },
    {
      "timestamp": "2023-12-19T12:03:17",
      "lat": 12.956778,
      "lon": 77.610824
    },
    {
      "timestamp": "2023-12-19T12:03:39",
      "lat": 12.956449,
      "lon": 77.610827
    },
    {
      "timestamp": "2023-12-19T12:03:56",
      "lat": 12.956119,
      "lon": 77.610831
    },
    {
      "timestamp": "2023-12-19T12:04:14",
      "lat": 12.95579,
      "lon": 77.610834
    },
    {
      "timestamp": "2023-12-19T12:04:38",
      "lat": 12.955463,
      "lon": 77.610819
    },
    {
      "timestamp": "2023-12-19T12:05:01",
      "lat": 12.955144,
      "lon": 77.610737
    },
    {
      "timestamp": "2023-12-19T12:05:17",
      "lat": 12.954825,
      "lon": 77.610654
    },
    {
      "timestamp": "2023-12-19T12:05:37",
      "lat": 12.954506,
      "lon": 77.610572
    },
    {
      "timestamp": "2023-12-19T12:05:52",
      "lat": 12.954376,
      "lon": 77.610819
    },
    {
      "timestamp": "2023-12-19T12:06:09",
      "lat": 12.954288,
      "lon": 77.611136
    },
    {
      "timestamp": "2023-12-19T12:06:24",
      "lat": 12.954186,
      "lon": 77.611449
    },
    {
      "timestamp": "2023-12-19T12:06:45",
      "lat": 12.953963,
      "lon": 77.611539
    },
    {
      "timestamp": "2023-12-19T12:07:03",
      "lat": 12.953781,
      "lon": 77.611693
    }
  ]
}