{
  "vehicle_id": "SE1_KA04AB5794_JETTING",
  "date": "2023-12-02",
  "points": [
    {
      "timestamp": "2023-12-02T09:20:00",
      "lat": 12.953277,
      "lon": 77.611805
    },
    {
      "timestamp": "2023-12-02T09:20:15",
      "lat": 12.953389,
      "lon": 77.61146
    },
    {
      "timestamp": "2023-12-02T09:20:36",
      "lat": 12.95366,
      "lon": 77.611435
    },
    {
      "timestamp": "2023-12-02T09:21:00",
      "lat": 12.954002,
      "lon": 77.611553
    },
    {
      "timestamp": "2023-12-02T09:21:17",
      "lat": 12.954215,
      "lon": 77.61138
    },
    {
      "timestamp": "2023-12-02T09:21:32",
      "lat": 12.954317,
      "lon": 77.611033
    },
    {
      "timestamp": "2023-12-02T09:21:53",
      "lat": 12.954414,
      "lon": 77.610684
    },
    {
      "timestamp": "2023-12-02T09:22:12",
      "lat": 12.954673,
      "lon": 77.610615
    },
    {
      "timestamp": "2023-12-02T09:22:33",
      "lat": 12.955023,
      "lon": 77.610706
    },
    {
      "timestamp": "2023-12-02T09:22:52",
      "lat": 12.955374,
      "lon": 77.610796
    },
    {
      "timestamp": "2023-12-02T09:23:09",
      "lat": 12.955731,
      "lon": 77.610834
    },
    {
      "timestamp": "2023-12-02T09:23:25",
      "lat": 12.956093,
      "lon": 77.610831
    },
    {
      "timestamp": "2023-12-02T09:23:46",
      "lat": 12.956455,
      "lon": 77.610827
    },
    {
      "timestamp": "2023-12-02T09:24:07",
      "lat": 12.956818,
      "lon": 77.610824
    },
    {
      "timestamp": "2023-12-02T09:24:30",
      "lat": 12.95718,
      "lon": 77.61082
    },
    {
      "timestamp": "2023-12-02T09:24:53",
      "lat": 12.957542,
      "lon": 77.610817
    },
    {
      "timestamp": "2023-12-02T09:25:15",
      "lat": 12.957904,
      "lon": 77.610813
    },
    {
      "timestamp": "2023-12-02T09:25:38",
      "lat": 12.958266,
      "lon": 77.61081
    },
    {
      "timestamp": "2023-12-02T09:26:01",
      "lat": 12.958628,
      "lon": 77.610814
    },
    {
      "timestamp": "2023-12-02T09:26:19",
      "lat": 12.958929,
      "lon": 77.61095
    },
    {
      "timestamp": "2023-12-02T09:26:37",
      "lat": 12.958918,
      "lon": 77.611312
    },
    {
      "timestamp": "2023-12-02T09:27:02",
      "lat": 12.958907,
      "lon": 77.611674
    },
    {
      "timestamp": "2023-12-02T09:27:24",
      "lat": 12.958896,
      "lon": 77.612036
    },
    {
      "timestamp": "2023-12-02T09:27:46",
      "lat": 12.958649,
      "lon": 77.612122
    },
    {
      "timestamp": "2023-12-02T09:28:11",
      "lat": 12.958289,
      "lon": 77.612078
    },
    {
      "timestamp": "2023-12-02T09:28:34",
      "lat": 12.95793,
      "lon": 77.612033
    },
    {
      "timestamp": "2023-12-02T09:28:50",
      "lat": 12.957571,
      "lon": 77.611987
    },
    {
      "timestamp": "2023-12-02T09:29:14",
      "lat": 12.957211,
      "lon": 77.611942
    },
    {
      "timestamp": "2023-12-02T09:29:39",
      "lat": 12.956852,
      "lon": 77.611897
    },
    {
      "timestamp": "2023-12-02T09:29:54",
      "lat": 12.956493,
      "lon": 77.611852
    },
    {
      "timestamp": "2023-12-02T09:30:15",
      "lat": 12.956133,
      "lon": 77.611813
    },
    {
      "timestamp": "2023-12-02T09:30:34",
      "lat": 12.955923,
      "lon": 77.612001
    },
    {
      "timestamp": "2023-12-02T09:30:55",
      "lat": 12.955808,
      "lon": 77.612345
    },
    {
      "timestamp": "2023-12-02T09:31:17",
      "lat": 12.955692,
      "lon": 77.612688
    },
    {
      "timestamp": "2023-12-02T09:31:34",
      "lat": 12.955581,
      "lon": 77.613032
    },
    {
      "timestamp": "2023-12-02T09:31:49",
      "lat": 12.955459,
      "lon": 77.613373
    },
    {
      "timestamp": "2023-12-02T09:32:09",
      "lat": 12.955287,
      "lon": 77.613691
    },
    {
      "timestamp": "2023-12-02T09:32:32",
      "lat": 12.955119,
      "lon": 77.614012
    },
    {
      "timestamp": "2023-12-02T09:32:50",
      "lat": 12.954986,
      "lon": 77.614347
    },
    {
      "timestamp": "2023-12-02T09:33:12",
      "lat": 12.954847,
      "lon": 77.614681
    },
    {
      "timestamp": "2023-12-02T09:33:34",
      "lat": 12.954726,
      "lon": 77.615022
    },
    {
      "timestamp": "2023-12-02T09:33:57",
      "lat": 12.954605,
      "lon": 77.615364
    },
    {
      "timestamp": "2023-12-02T09:34:16",
      "lat": 12.954483,
      "lon": 77.615705
    },
    {
      "timestamp": "2023-12-02T09:34:39",
      "lat": 12.954342,
      "lon": 77.616038
    },
    {
      "timestamp": "2023-12-02T09:34:59",
      "lat": 12.954207,
      "lon": 77.616374
    },
    {
      "timestamp": "2023-12-02T09:35:24",
      "lat": 12.954056,
      "lon": 77.616703
    },
    {
      "timestamp": "2023-12-02T09:35:47",
      "lat": 12.953911,
      "lon": 77.617035
    },
    {
      "timestamp": "2023-12-02T09:36:03",
      "lat": 12.95377,
      "lon": 77.617369
    },
    {
      "timestamp": "2023-12-02T09:36:24",
      "lat": 12.953612,
      "lon": 77.617695
    },
    {
      "timestamp": "2023-12-02T09:36:47",
      "lat": 12.95332,
      "lon": 77.617803
    },
    {
      "timestamp": "2023-12-02T09:37:08",
      "lat": 12.952962,
      "lon": 77.617847
    },
    {
      "timestamp": "2023-12-02T09:37:32",
      "lat": 12.952692,
      "lon": 77.618063
    },
    {
      "timestamp": "2023-12-02T09:37:55",
      "lat": 12.95249,
      "lon": 77.618363
    },
    {
      "timestamp": "2023-12-02T09:38:17",
      "lat": 12.952292,
      "lon": 77.618667
    },
    {
      "timestamp": "2023-12-02T09:38:41",
      "lat": 12.952219,
      "lon": 77.618828
    },
    {
      "timestamp": "2023-12-02T09:39:00",
      "lat": 12.951862,
      "lon": 77.618844
    },
    {
      "timestamp": "2023-12-02T09:39:25",
      "lat": 12.951558,
      "lon": 77.618839
    },
    {
      "timestamp": "2023-12-02T09:39:44",
      "lat": 12.951281,
      "lon": 77.61861
    },
    {
      "timestamp": "2023-12-02T09:40:05",
      "lat": 12.95098,
      "lon": 77.618408
    },
    {
      "timestamp": "2023-12-02T09:40:30",
      "lat": 12.950679,
      "lon": 77.618206
    },
    {
      "timestamp": "2023-12-02T09:40:52",
      "lat": 12.950379,
      "lon": 77.618004
    },
    {
      "timestamp": "2023-12-02T09:41:15",
      "lat": 12.950071,
      "lon": 77.617816
    },
    {
      "timestamp": "2023-12-02T09:41:36",
      "lat": 12.949755,
      "lon": 77.617639
    },
    {
      "timestamp": "2023-12-02T09:41:52",
      "lat": 12.94944,
      "lon": 77.617461
    },
    {
      "timestamp": "2023-12-02T09:42:13",
      "lat": 12.94913,
      "lon": 77.617275
    },
    {
      "timestamp": "2023-12-02T09:42:34",
      "lat": 12.948812,
      "lon": 77.617104
    },
    {
      "timestamp": "2023-12-02T09:42:53",
      "lat": 12.94848,
      "lon": 77.616999
    },
    {
      "timestamp": "2023-12-02T09:43:12",
      "lat": 12.948305,
      "lon": 77.617316
    },
    {
      "timestamp": "2023-12-02T09:43:32",
      "lat": 12.948129,
      "lon": 77.617632
    },
    {
      "timestamp": "2023-12-02T09:43:50",
      "lat": 12.947953,
      "lon": 77.617949
    },
    {
      "timestamp": "2023-12-02T09:44:15",
      "lat": 12.947778,
      "lon": 77.618265
    },
    {
      "timestamp": "2023-12-02T09:44:35",
      "lat": 12.947492,
      "lon": 77.618313
    },
    {
      "timestamp": "2023-12-02T09:44:52",
      "lat": 12.947144,
      "lon": 77.618214
    },
    {
      "timestamp": "2023-12-02T09:45:12",
      "lat": 12.946917,
      "lon": 77.618399
    },
    {
      "timestamp": "2023-12-02T09:45:28",
      "lat": 12.946635,
      "lon": 77.61844
    },
    {
      "timestamp": "2023-12-02T09:45:53",
      "lat": 12.94629,
      "lon": 77.618329
    },
    {
      "timestamp": "2023-12-02T09:46:12",
      "lat": 12.946053,
      "lon": 77.618511
    },
    {
      "timestamp": "2023-12-02T09:46:35",
      "lat": 12.945777,
      "lon": 77.618664
    },
    {
      "timestamp": "2023-12-02T09:46:58",
      "lat": 12.945546,
      "lon": 77.618942
    },
    {
      "timestamp": "2023-12-02T09:47:14",
      "lat": 12.94532,
      "lon": 77.619217
    },
    {
      "timestamp": "2023-12-02T09:47:32",
      "lat": 12.944974,
      "lon": 77.619108
    },
    {
      "timestamp": "2023-12-02T09:47:54",
      "lat": 12.944626,
      "lon": 77.619008
    },
    {
      "timestamp": "2023-12-02T09:48:15",
      "lat": 12.944275,
      "lon": 77.61892
    },
    {
      "timestamp": "2023-12-02T09:48:35",
      "lat": 12.943956,
      "lon": 77.618857
    },
    {
      "timestamp": "2023-12-02T09:48:50",
      "lat": 12.944039,
      "lon": 77.61921
    },
    {
      "timestamp": "2023-12-02T09:49:12",
      "lat": 12.944018,
      "lon": 77.619554
    },
    {
      "timestamp": "2023-12-02T09:49:28",
      "lat": 12.944071,
      "lon": 77.619815
    },
    {
      "timestamp": "2023-12-02T09:49:47",
      "lat": 12.944401,
      "lon": 77.619965
    },
    {
      "timestamp": "2023-12-02T09:50:12",
      "lat": 12.944705,
      "lon": 77.620116
    },
    {
      "timestamp": "2023-12-02T09:50:37",
      "lat": 12.944488,
      "lon": 77.620406
    },
    {
      "timestamp": "2023-12-02T09:51:00",
      "lat": 12.94427,
      "lon": 77.620696
    },
    {
      "timestamp": "2023-12-02T09:51:22",
      "lat": 12.944038,
      "lon": 77.620974
    },
    {
      "timestamp": "2023-12-02T09:51:37",
      "lat": 12.943802,
      "lon": 77.621249
    },
    {
      "timestamp": "2023-12-02T09:51:59",
      "lat": 12.943565,
      "lon": 77.621522
    },
    {
      "timestamp": "2023-12-02T09:52:16",
      "lat": 12.943327,
      "lon": 77.621796
    },
    {
      "timestamp": "2023-12-02T09:52:36",
      "lat": 12.943081,
      "lon": 77.622061
    },
    {
      "timestamp": "2023-12-02T09:52:57",
      "lat": 12.942841,
      "lon": 77.622332
    },
    {
      "timestamp": "2023-12-02T09:53:17",
      "lat": 12.942601,
      "lon": 77.622603
    },
    {
      "timestamp": "2023-12-02T09:53:32",
      "lat": 12.942449,
      "lon": 77.622877
    },
    {
      "timestamp": "2023-12-02T09:53:52",
      "lat": 12.942208,
      "lon": 77.623147
    },
    {
      "timestamp": "2023-12-02T09:54:08",
      "lat": 12.941959,
      "lon": 77.62341
    },
    {
      "timestamp": "2023-12-02T09:54:30",
      "lat": 12.94171,
      "lon": 77.623673
    },
    {
      "timestamp": "2023-12-02T09:54:52",
      "lat": 12.941461,
      "lon": 77.623936
    },
    {
      "timestamp": "2023-12-02T09:55:10",
      "lat": 12.941211,
      "lon": 77.624198
    },
    {
      "timestamp": "2023-12-02T09:55:35",
      "lat": 12.940953,
      "lon": 77.624452
    },
    {
      "timestamp": "2023-12-02T09:55:54",
      "lat": 12.9407,
      "lon": 77.624712
    },
    {
      "timestamp": "2023-12-02T09:56:19",
      "lat": 12.940445,
      "lon": 77.624968
    },
    {
      "timestamp": "2023-12-02T09:56:41",
      "lat": 12.940173,
      "lon": 77.625207
    },
    {
      "timestamp": "2023-12-02T09:56:58",
      "lat": 12.939919,
      "lon": 77.625435
    },
    {
      "timestamp": "2023-12-02T09:57:23",
      "lat": 12.940168,
      "lon": 77.625698
    },
    {
      "timestamp": "2023-12-02T09:57:44",
      "lat": 12.94038,
      "lon": 77.625984
    },
    {
      "timestamp": "2023-12-02T09:58:07",
      "lat": 12.940491,
      "lon": 77.626329
    },
    {
      "timestamp": "2023-12-02T09:58:28",
      "lat": 12.940604,
      "lon": 77.626673
    },
    {
      "timestamp": "2023-12-02T09:58:50",
      "lat": 12.940746,
      "lon": 77.627005
    },
    {
      "timestamp": "2023-12-02T09:59:07",
      "lat": 12.940858,
      "lon": 77.62735
    },
    {
      "timestamp": "2023-12-02T09:59:28",
      "lat": 12.940934,
      "lon": 77.627676
    },
    {
      "timestamp": "2023-12-02T09:59:43",
      "lat": 12.940576,
      "lon": 77.62773
    },
    {
      "timestamp": "2023-12-02T10:00:07",
      "lat": 12.940359,
      "lon": 77.627897
    },
    {
      "timestamp": "2023-12-02T10:00:26",
      "lat": 12.940411,
      "lon": 77.628255
    },
    {
      "timestamp": "2023-12-02T10:00:43",
      "lat": 12.940151,
      "lon": 77.628385
    },
    {
      "timestamp": "2023-12-02T10:01:03",
      "lat": 12.940168,
      "lon": 77.628715
    },
    {
      "timestamp": "2023-12-02T10:01:26",
      "lat": 12.940174,
      "lon": 77.629077
    },
    {
      "timestamp": "2023-12-02T10:01:49",
      "lat": 12.940201,
      "lon": 77.629438
    },
    {
      "timestamp": "2023-12-02T10:02:08",
      "lat": 12.939984,
      "lon": 77.629671
    },
    {
      "timestamp": "2023-12-02T10:02:26",
      "lat": 12.939723,
      "lon": 77.629919
    },
    {
      "timestamp": "2023-12-02T10:02:43",
      "lat": 12.9395,
      "lon": 77.630002
    },
    {
      "timestamp": "2023-12-02T10:03:04",
      "lat": 12.939158,
      "lon": 77.629982
    },
    {
      "timestamp": "2023-12-02T10:03:27",
      "lat": 12.938946,
      "lon": 77.630003
    },
    {
      "timestamp": "2023-12-02T10:03:44",
      "lat": 12.939294,
      "lon": 77.630102
    },
    {
      "timestamp": "2023-12-02T10:03:59",
      "lat": 12.939436,
      "lon": 77.630282
    },
    {
      "timestamp": "2023-12-02T10:04:14",
      "lat": 12.939183,
      "lon": 77.63053
    },
    {
      "timestamp": "2023-12-02T10:04:32",
      "lat": 12.938962,
      "lon": 77.630793
    },
    {
      "timestamp": "2023-12-02T10:04:54",
      "lat": 12.938601,
      "lon": 77.630821
    },
    {
      "timestamp": "2023-12-02T10:05:15",
      "lat": 12.938569,
      "lon": 77.631144
    },
    {
      "timestamp": "2023-12-02T10:05:38",
      "lat": 12.938577,
      "lon": 77.631506
    },
    {
      "timestamp": "2023-12-02T10:06:00",
      "lat": 12.938582,
      "lon": 77.631869
    },
    {
      "timestamp": "2023-12-02T10:06:17",
      "lat": 12.938579,
      "lon": 77.632231
    },
    {
      "timestamp": "2023-12-02T10:06:35",
      "lat": 12.938573,
      "lon": 77.632593
    },
    {
      "timestamp": "2023-12-02T10:06:56",
      "lat": 12.938783,
      "lon": 77.632756
    },
    {
      "timestamp": "2023-12-02T10:07:12",
      "lat": 12.939118,
      "lon": 77.632733
    },
    {
      "timestamp": "2023-12-02T10:07:35",
      "lat": 12.93946,
      "lon": 77.632612
    },
    {
      "timestamp": "2023-12-02T10:07:56",
      "lat": 12.939801,
      "lon": 77.632491
    },
    {
      "timestamp": "2023-12-02T10:08:11",
      "lat": 12.940142,
      "lon": 77.632371
    },
    {
      "timestamp": "2023-12-02T10:08:35",
      "lat": 12.940484,
      "lon": 77.63225
    },
    {
      "timestamp": "2023-12-02T10:08:57",
      "lat": 12.940833,
      "lon": 77.632163
    },
    {
      "timestamp": "2023-12-02T10:09:20",
      "lat": 12.941176,
      "lon": 77.632254
    },
    {
      "timestamp": "2023-12-02T10:09:45",
      "lat": 12.941496,
      "lon": 77.632127
    },
    {
      "timestamp": "2023-12-02T10:10:02",
      "lat": 12.941815,
      "lon": 77.631956
    },
    {
      "timestamp": "2023-12-02T10:10:24",
      "lat": 12.942135,
      "lon": 77.631785
    },
    {
      "timestamp": "2023-12-02T10:10:39",
      "lat": 12.942452,
      "lon": 77.631611
    },
    {
      "timestamp": "2023-12-02T10:10:54",
      "lat": 12.942761,
      "lon": 77.631421
    },
    {
      "timestamp": "2023-12-02T10:11:17",
      "lat": 12.943035,
      "lon": 77.631204
    },
    {
      "timestamp": "2023-12-02T10:11:32",
      "lat": 12.943323,
      "lon": 77.631006
    },
    {
      "timestamp": "2023-12-02T10:11:49",
      "lat": 12.943643,
      "lon": 77.630836
    },
    {
      "timestamp": "2023-12-02T10:12:09",
      "lat": 12.943963,
      "lon": 77.630666
    },
    {
      "timestamp": "2023-12-02T10:12:26",
      "lat": 12.944279,
      "lon": 77.630489
    },
    {
      "timestamp": "2023-12-02T10:12:43",
      "lat": 12.944587,
      "lon": 77.630299
    },
    {
      "timestamp": "2023-12-02T10:13:07",
      "lat": 12.944899,
      "lon": 77.630241
    },
    {
      "timestamp": "2023-12-02T10:13:26",
      "lat": 12.945196,
      "lon": 77.630034
    },
    {
      "timestamp": "2023-12-02T10:13:43",
      "lat": 12.945493,
      "lon": 77.629827
    },
    {
      "timestamp": "2023-12-02T10:14:02",
      "lat": 12.945813,
      "lon": 77.62966
    },
    {
      "timestamp": "2023-12-02T10:14:22",
      "lat": 12.946139,
      "lon": 77.629502
    },
    {
      "timestamp": "2023-12-02T10:14:46",
      "lat": 12.946438,
      "lon": 77.629297
    },
    {
      "timestamp": "2023-12-02T10:15:08",
      "lat": 12.946735,
      "lon": 77.62909
    },
    {
      "timestamp": "2023-12-02T10:15:25",
      "lat": 12.947032,
      "lon": 77.628883
    },
    {
      "timestamp": "2023-12-02T10:15:49",
      "lat": 12.94732,
      "lon": 77.628663
    },
    {
      "timestamp": "2023-12-02T10:16:07",
      "lat": 12.947625,
      "lon": 77.628468
    },
    {
      "timestamp": "2023-12-02T10:16:30",
      "lat": 12.947935,
      "lon": 77.628281
    },
    {
      "timestamp": "2023-12-02T10:16:47",
      "lat": 12.948252,
      "lon": 77.628107
    },
    {
      "timestamp": "2023-12-02T10:17:07",
      "lat": 12.948569,
      "lon": 77.627932
    },
    {
      "timestamp": "2023-12-02T10:17:27",
      "lat": 12.948883,
      "lon": 77.627752
    },
    {
      "timestamp": "2023-12-02T10:17:47",
      "lat": 12.949171,
      "lon": 77.627534
    },
    {
      "timestamp": "2023-12-02T10:18:02",
      "lat": 12.949427,
      "lon": 77.627278
    },
    {
      "timestamp": "2023-12-02T10:18:19",
      "lat": 12.94973,
      "lon": 77.627083
    },
    {
      "timestamp": "2023-12-02T10:18:36",
      "lat": 12.950053,
      "lon": 77.626919
    },
    {
      "timestamp": "2023-12-02T10:18:57",
      "lat": 12.950371,
      "lon": 77.626745
    },
    {
      "timestamp": "2023-12-02T10:19:17",
      "lat": 12.950686,
      "lon": 77.626567
    },
    {
      "timestamp": "2023-12-02T10:19:37",
      "lat": 12.951,
      "lon": 77.626386
    },
    {
      "timestamp": "2023-12-02T10:19:54",
      "lat": 12.951329,
      "lon": 77.62624
    },
    {
      "timestamp": "2023-12-02T10:20:15",
      "lat": 12.95168,
      "lon": 77.626152
    },
    {
      "timestamp": "2023-12-02T10:20:35",
      "lat": 12.952033,
      "lon": 77.626069
    },
    {
      "timestamp": "2023-12-02T10:20:51",
      "lat": 12.952356,
      "lon": 77.625906
    },
    {
      "timestamp": "2023-12-02T10:21:10",
      "lat": 12.952677,
      "lon": 77.625738
    },
    {
      "timestamp": "2023-12-02T10:21:29",
      "lat": 12.952979,
      "lon": 77.625539
    },
    {
      "timestamp": "2023-12-02T10:21:50",
      "lat": 12.953272,
      "lon": 77.625328
    },
    {
      "timestamp": "2023-12-02T10:22:10",
      "lat": 12.953545,
      "lon": 77.625089
    },
    {
      "timestamp": "2023-12-02T10:22:28",
      "lat": 12.95381,
      "lon": 77.624846
    },
    {
      "timestamp": "2023-12-02T10:22:46",
      "lat": 12.954155,
      "lon": 77.624737
    },
    {
      "timestamp": "2023-12-02T10:23:05",
      "lat": 12.954501,
      "lon": 77.624628
    },
    {
      "timestamp": "2023-12-02T10:23:25",
      "lat": 12.954854,
      "lon": 77.624559
    },
    {
      "timestamp": "2023-12-02T10:23:48",
      "lat": 12.955178,
      "lon": 77.624407
    },
    {
      "timestamp": "2023-12-02T10:24:03",
      "lat": 12.955487,
      "lon": 77.624216
    },
    {
      "timestamp": "2023-12-02T10:24:25",
      "lat": 12.955797,
      "lon": 77.624029
    },
    {
      "timestamp": "2023-12-02T10:24:47",
      "lat": 12.956145,
      "lon": 77.623982
    },
    {
      "timestamp": "2023-12-02T10:25:06",
      "lat": 12.956492,
      "lon": 77.62407
    },
    {
      "timestamp": "2023-12-02T10:25:27",
      "lat": 12.956781,
      "lon": 77.624279
    },
    {
      "timestamp": "2023-12-02T10:25:44",
      "lat": 12.95701,
      "lon": 77.624517
    },
    {
      "timestamp": "2023-12-02T10:26:00",
      "lat": 12.957176,
      "lon": 77.624839
    },
    {
      "timestamp": "2023-12-02T10:26:16",
      "lat": 12.957451,
      "lon": 77.624648
    },
    {
      "timestamp": "2023-12-02T10:26:41",
      "lat": 12.957734,
      "lon": 77.624421
    },
    {
      "timestamp": "2023-12-02T10:27:00",
      "lat": 12.958016,
      "lon": 77.624195
    },
    {
      "timestamp": "2023-12-02T10:27:22",
      "lat": 12.958299,
      "lon": 77.623969
    },
    {
      "timestamp": "2023-12-02T10:27:46",
      "lat": 12.958414,
      "lon": 77.623698
    },
    {
      "timestamp": "2023-12-02T10:28:09",
      "lat": 12.958279,
      "lon": 77.623362
    },
    {
      "timestamp": "2023-12-02T10:28:27",
      "lat": 12.958144,
      "lon": 77.623026
    },
    {
      "timestamp": "2023-12-02T10:28:48",
      "lat": 12.958009,
      "lon": 77.62269
    },
    {
      "timestamp": "2023-12-02T10:29:07",
      "lat": 12.957875,
      "lon": 77.622353
    },
    {
      "timestamp": "2023-12-02T10:29:23",
      "lat": 12.95774,
      "lon": 77.622017
    },
    {
      "timestamp": "2023-12-02T10:29:42",
      "lat": 12.95741,
      "lon": 77.622156
    },
    {
      "timestamp": "2023-12-02T10:30:04",
      "lat": 12.957081,
      "lon": 77.622308
    },
    {
      "timestamp": "2023-12-02T10:30:29",
      "lat": 12.956776,
      "lon": 77.6224
    },
    {
      "timestamp": "2023-12-02T10:30:51",
      "lat": 12.956635,
      "lon": 77.622066
    },
    {
      "timestamp": "2023-12-02T10:31:15",
      "lat": 12.956458,
      "lon": 77.621829
    },
    {
      "timestamp": "2023-12-02T10:31:38",
      "lat": 12.956308,
      "lon": 77.6215
    },
    {
      "timestamp": "2023-12-02T10:31:59",
      "lat": 12.956176,
      "lon": 77.621166
    },
    {
      "timestamp": "2023-12-02T10:32:22",
      "lat": 12.956397,
      "lon": 77.621088
    },
    {
      "timestamp": "2023-12-02T10:32:43",
      "lat": 12.956584,
      "lon": 77.620952
    },
    {
      "timestamp": "2023-12-02T10:33:02",
      "lat": 12.956586,
      "lon": 77.62059
    },
    {
      "timestamp": "2023-12-02T10:33:22",
      "lat": 12.956589,
      "lon": 77.620228
    },
    {
      "timestamp": "2023-12-02T10:33:43",
      "lat": 12.956592,
      "lon": 77.619866
    },
    {
      "timestamp": "2023-12-02T10:34:08",
      "lat": 12.956589,
      "lon": 77.619504
    },
    {
      "timestamp": "2023-12-02T10:34:31",
      "lat": 12.956674,
      "lon": 77.619155
    },
    {
      "timestamp": "2023-12-02T10:34:52",
      "lat": 12.95655,
      "lon": 77.618901
    },
    {
      "timestamp": "2023-12-02T10:35:12",
      "lat": 12.956485,
      "lon": 77.618545
    },
    {
      "timestamp": "2023-12-02T10:35:28",
      "lat": 12.95642,
      "lon": 77.618189
    },
    {
      "timestamp": "2023-12-02T10:35:43",
      "lat": 12.956457,
      "lon": 77.617869
    },
    {
      "timestamp": "2023-12-02T10:36:04",
      "lat": 12.956754,
      "lon": 77.617662
    },
    {
      "timestamp": "2023-12-02T10:36:25",
      "lat": 12.957001,
      "lon": 77.617412
    },
    {
      "timestamp": "2023-12-02T10:36:40",
      "lat": 12.957056,
      "lon": 77.617055
    },
    {
      "timestamp": "2023-12-02T10:36:57",
      "lat": 12.957103,
      "lon": 77.616742
    },
    {
      "timestamp": "2023-12-02T10:37:20",
      "lat": 12.957455,
      "lon": 77.616666
    },
    {
      "timestamp": "2023-12-02T10:37:35",
      "lat": 12.957816,
      "lon": 77.616635
    },
    {
      "timestamp": "2023-12-02T10:37:57",
      "lat": 12.957976,
      "lon": 77.616404
    },
    {
      "timestamp": "2023-12-02T10:38:17",
      "lat": 12.958012,
      "lon": 77.616044
    },
    {
      "timestamp": "2023-12-02T10:38:41",
      "lat": 12.95805,
      "lon": 77.615684
    },
    {
      "timestamp": "2023-12-02T10:39:06",
      "lat": 12.958089,
      "lon": 77.615323
    },
    {
      "timestamp": "2023-12-02T10:39:24",
      "lat": 12.958128,
      "lon": 77.614963
    },
    {
      "timestamp": "2023-12-02T10:39:48",
      "lat": 12.958173,
      "lon": 77.614604
    },
    {
      "timestamp": "2023-12-02T10:40:07",
      "lat": 12.958217,
      "lon": 77.614245
    },
    {
      "timestamp": "2023-12-02T10:40:30",
      "lat": 12.958258,
      "lon": 77.613885
    },
    {
      "timestamp": "2023-12-02T10:40:46",
      "lat": 12.9583,
      "lon": 77.613525
    },
    {
      "timestamp": "2023-12-02T10:41:06",
      "lat": 12.958341,
      "lon": 77.613165
    },
    {
      "timestamp": "2023-12-02T10:41:31",
      "lat": 12.958382,
      "lon": 77.612805
    },
    {
      "timestamp": "2023-12-02T10:41:48",
      "lat": 12.958424,
      "lon": 77.612446
    },
    {
      "timestamp": "2023-12-02T10:42:10",
      "lat": 12.958478,
      "lon": 77.612102
    },
    {
      "timestamp": "2023-12-02T10:42:28",
      "lat": 12.958837,
      "lon": 77.612145
    },
    {
      "timestamp": "2023-12-02T10:42:45",
      "lat": 12.958902,
      "lon": 77.611846
    },
    {
      "timestamp": "2023-12-02T10:43:10",
      "lat": 12.958913,
      "lon": 77.611484
    },
    {
      "timestamp": "2023-12-02T10:43:35",
      "lat": 12.958924,
      "lon": 77.611122
    },
    {
      "timestamp": "2023-12-02T10:43:51",
      "lat": 12.9588,
      "lon": 77.61082
    },
    {
      "timestamp": "2023-12-02T10:44:07",
      "lat": 12.95847,
      "lon": 77.610782
    },
    {
      "timestamp": "2023-12-02T10:44:30",
      "lat": 12.958539,
      "lon": 77.610427
    },
    {
      "timestamp": "2023-12-02T10:44:47",
      "lat": 12.958608,
      "lon": 77.610071
    },
    {
      "timestamp": "2023-12-02T10:45:03",
      "lat": 12.958545,
      "lon": 77.609807
    },
    {
      "timestamp": "2023-12-02T10:45:19",
      "lat": 12.958188,
      "lon": 77.60975
    },
    {
      "timestamp": "2023-12-02T10:45:37",
      "lat": 12.957829,
      "lon": 77.6097
    },
    {
      "timestamp": "2023-12-02T10:45:53",
      "lat": 12.95747,
      "lon": 77.60965
    },
    {
      "timestamp": "2023-12-02T10:46:10",
      "lat": 12.957113,
      "lon": 77.609588
    },
    {
      "timestamp": "2023-12-02T10:46:31",
      "lat": 12.956757,
      "lon": 77.609527
    },
    {
      "timestamp": "2023-12-02T10:46:50",
      "lat": 12.956399,
      "lon": 77.609471
    },
    {
      "timestamp": "2023-12-02T10:47:13",
      "lat": 12.956039,
      "lon": 77.609427
    },
    {
      "timestamp": "2023-12-02T10:47:31",
      "lat": 12.95568,
      "lon": 77.609379
    },
    {
      "timestamp": "2023-12-02T10:47:54",
      "lat": 12.955322,
      "lon": 77.609329
    },
    {
      "timestamp": "2023-12-02T10:48:17",
      "lat": 12.954963,
      "lon": 77.609279
    },
    {
      "timestamp": "2023-12-02T10:48:41",
      "lat": 12.954979,
      "lon": 77.608944
    },
    {
      "timestamp": "2023-12-02T10:49:04",
      "lat": 12.955025,
      "lon": 77.608585
    },
    {
      "timestamp": "2023-12-02T10:49:19",
      "lat": 12.955073,
      "lon": 77.608226
    },
    {
      "timestamp": "2023-12-02T10:49:41",
      "lat": 12.955122,
      "lon": 77.607867
    },
    {
      "timestamp": "2023-12-02T10:50:05",
      "lat": 12.95517,
      "lon": 77.607508
    },
    {
      "timestamp": "2023-12-02T10:50:26",
      "lat": 12.954855,
      "lon": 77.607415
    },
    {
      "timestamp": "2023-12-02T10:50:48",
      "lat": 12.954499,
      "lon": 77.607352
    },
    {
      "timestamp": "2023-12-02T10:51:05",
      "lat": 12.954142,
      "lon": 77.607289
    },
    {
      "timestamp": "2023-12-02T10:51:22",
      "lat": 12.953797,
      "lon": 77.607284
    },
    {
      "timestamp": "2023-12-02T10:51:45",
      "lat": 12.953485,
      "lon": 77.60729
    },
    {
      "timestamp": "2023-12-02T10:52:08",
      "lat": 12.953132,
      "lon": 77.607211
    },
    {
      "timestamp": "2023-12-02T10:52:33",
      "lat": 12.952778,
      "lon": 77.607132
    },
    {
      "timestamp": "2023-12-02T10:52:57",
      "lat": 12.95242,
      "lon": 77.607172
    },
    {
      "timestamp": "2023-12-02T10:53:21",
      "lat": 12.952064,
      "lon": 77.60716
    },
    {
      "timestamp": "2023-12-02T10:53:39",
      "lat": 12.95233,
      "lon": 77.607186
    },
    {
      "timestamp": "2023-12-02T10:54:04",
      "lat": 12.952689,
      "lon": 77.607132
    },
    {
      "timestamp": "2023-12-02T10:54:25",
      "lat": 12.953043,
      "lon": 77.607191
    },
    {
      "timestamp": "2023-12-02T10:54:50",
      "lat": 12.953397,
      "lon": 77.607271
    },
    {
      "timestamp": "2023-12-02T10:55:09",
      "lat": 12.953751,
      "lon": 77.607347
    },
    {
      "timestamp": "2023-12-02T10:55:30",
      "lat": 12.954052,
      "lon": 77.607276
    },
    {
      "timestamp": "2023-12-02T10:55:45",
      "lat": 12.95441,
      "lon": 77.607335
    },
    {
      "timestamp": "2023-12-02T10:56:00",
      "lat": 12.954766,
      "lon": 77.6074
    },
    {
      "timestamp": "2023-12-02T10:56:21",
      "lat": 12.955123,
      "lon": 77.607462
    },
    {
      "timestamp": "2023-12-02T10:56:40",
      "lat": 12.955481,
      "lon": 77.607517
    },
    {
      "timestamp": "2023-12-02T10:57:03",
      "lat": 12.95576,
      "lon": 77.607471
    },
    {
      "timestamp": "2023-12-02T10:57:20",
      "lat": 12.955789,
      "lon": 77.60711
    },
    {
      "timestamp": "2023-12-02T10:57:41",
      "lat": 12.955819,
      "lon": 77.606749
    },
    {
      "timestamp": "2023-12-02T10:58:00",
      "lat": 12.955854,
      "lon": 77.606388
    },
    {
      "timestamp": "2023-12-02T10:58:15",
      "lat": 12.955871,
      "lon": 77.606028
    },
    {
      "timestamp": "2023-12-02T10:58:38",
      "lat": 12.955636,
      "lon": 77.605859
    },
    {
      "timestamp": "2023-12-02T10:58:53",
      "lat": 12.955506,
      "lon": 77.605634
    },
    {
      "timestamp": "2023-12-02T10:59:09",
      "lat": 12.955148,
      "lon": 77.605576
    },
    {
      "timestamp": "2023-12-02T10:59:29",
      "lat": 12.954791,
      "lon": 77.605518
    },
    {
      "timestamp": "2023-12-02T10:59:50",
      "lat": 12.954432,
      "lon": 77.605473
    },
    {
      "timestamp": "2023-12-02T11:00:14",
      "lat": 12.954072,
      "lon": 77.605427
    },
    {
      "timestamp": "2023-12-02T11:00:35",
      "lat": 12.953713,
      "lon": 77.605381
    },
    {
      "timestamp": "2023-12-02T11:00:55",
      "lat": 12.953354,
      "lon": 77.605336
    },
    {
      "timestamp": "2023-12-02T11:01:15",
      "lat": 12.952994,
      "lon": 77.60529
    },
    {
      "timestamp": "2023-12-02T11:01:38",
      "lat": 12.952635,
      "lon": 77.60525
    },
    {
      "timestamp": "2023-12-02T11:02:02",
      "lat": 12.952274,
      "lon": 77.605219
    },
    {
      "timestamp": "2023-12-02T11:02:27",
      "lat": 12.951913,
      "lon": 77.605191
    },
    {
      "timestamp": "2023-12-02T11:02:51",
      "lat": 12.951564,
      "lon": 77.605283
    },
    {
      "timestamp": "2023-12-02T11:03:07",
      "lat": 12.951219,
      "lon": 77.605394
    },
    {
      "timestamp": "2023-12-02T11:03:22",
      "lat": 12.950876,
      "lon": 77.60551
    },
    {
      "timestamp": "2023-12-02T11:03:42",
      "lat": 12.950537,
      "lon": 77.605637
    },
    {
      "timestamp": "2023-12-02T11:04:06",
      "lat": 12.95021,
      "lon": 77.605791
    },
    {
      "timestamp": "2023-12-02T11:04:31",
      "lat": 12.949872,
      "lon": 77.605921
    },
    {
      "timestamp": "2023-12-02T11:04:51",
      "lat": 12.949521,
      "lon": 77.606003
    },
    {
      "timestamp": "2023-12-02T11:05:15",
      "lat": 12.94918,
      "lon": 77.606127
    },
    {
      "timestamp": "2023-12-02T11:05:33",
      "lat": 12.948833,
      "lon": 77.606231
    },
    {
      "timestamp": "2023-12-02T11:05:57",
      "lat": 12.948487,
      "lon": 77.606337
    },
    {
      "timestamp": "2023-12-02T11:06:20",
      "lat": 12.94814,
      "lon": 77.606441
    },
    {
      "timestamp": "2023-12-02T11:06:37",
      "lat": 12.947793,
      "lon": 77.606545
    },
    {
      "timestamp": "2023-12-02T11:06:52",
      "lat": 12.947446,
      "lon": 77.606649
    },
    {
      "timestamp": "2023-12-02T11:07:12",
      "lat": 12.9471,
      "lon": 77.606754
    },
    {
      "timestamp": "2023-12-02T11:07:35",
      "lat": 12.946753,
      "lon": 77.606858
    },
    {
      "timestamp": "2023-12-02T11:07:55",
      "lat": 12.946406,
      "lon": 77.606962
    },
    {
      "timestamp": "2023-12-02T11:08:16",
      "lat": 12.946059,
      "lon": 77.607066
    },
    {
      "timestamp": "2023-12-02T11:08:31",
      "lat": 12.945711,
      "lon": 77.607168
    },
    {
      "timestamp": "2023-12-02T11:08:48",
      "lat": 12.945364,
      "lon": 77.607269
    },
    {
      "timestamp": "2023-12-02T11:09:05",
      "lat": 12.945016,
      "lon": 77.607371
    },
    {
      "timestamp": "2023-12-02T11:09:22",
      "lat": 12.944817,
      "lon": 77.607588
    },
    {
      "timestamp": "2023-12-02T11:09:41",
      "lat": 12.944708,
      "lon": 77.607926
    },
    {
      "timestamp": "2023-12-02T11:10:03",
      "lat": 12.94461,
      "lon": 77.60827
    },
    {
      "timestamp": "2023-12-02T11:10:28",
      "lat": 12.944561,
      "lon": 77.608629
    },
    {
      "timestamp": "2023-12-02T11:10:46",
      "lat": 12.944499,
      "lon": 77.608983
    },
    {
      "timestamp": "2023-12-02T11:11:01",
      "lat": 12.944443,
      "lon": 77.609341
    },
    {
      "timestamp": "2023-12-02T11:11:16",
      "lat": 12.944317,
      "lon": 77.609605
    },
    {
      "timestamp": "2023-12-02T11:11:31",
      "lat": 12.944065,
      "lon": 77.6097
    },
    {
      "timestamp": "2023-12-02T11:11:55",
      "lat": 12.943981,
      "lon": 77.610052
    },
    {
      "timestamp": "2023-12-02T11:12:17",
      "lat": 12.943906,
      "lon": 77.610406
    },
    {
      "timestamp": "2023-12-02T11:12:38",
      "lat": 12.943755,
      "lon": 77.610731
    },
    {
      "timestamp": "2023-12-02T11:12:54",
      "lat": 12.943607,
      "lon": 77.61106
    },
    {
      "timestamp": "2023-12-02T11:13:09",
      "lat": 12.943503,
      "lon": 77.611406
    },
    {
      "timestamp": "2023-12-02T11:13:27",
      "lat": 12.943422,
      "lon": 77.611758
    },
    {
      "timestamp": "2023-12-02T11:13:43",
      "lat": 12.943378,
      "lon": 77.612116
    },
    {
      "timestamp": "2023-12-02T11:14:07",
      "lat": 12.94328,
      "lon": 77.612465
    },
    {
      "timestamp": "2023-12-02T11:14:24",
      "lat": 12.943171,
      "lon": 77.61281
    },
    {
      "timestamp": "2023-12-02T11:14:48",
      "lat": 12.943025,
      "lon": 77.613138
    },
    {
      "timestamp": "2023-12-02T11:15:10",
      "lat": 12.942862,
      "lon": 77.613454
    },
    {
      "timestamp": "2023-12-02T11:15:34",
      "lat": 12.942747,
      "lon": 77.613797
    },
    {
      "timestamp": "2023-12-02T11:15:54",
      "lat": 12.942618,
      "lon": 77.614135
    },
    {
      "timestamp": "2023-12-02T11:16:19",
      "lat": 12.942462,
      "lon": 77.614461
    },
    {
      "timestamp": "2023-12-02T11:16:42",
      "lat": 12.9423,
      "lon": 77.614785
    },
    {
      "timestamp": "2023-12-02T11:17:04",
      "lat": 12.942153,
      "lon": 77.615116
    },
    {
      "timestamp": "2023-12-02T11:17:28",
      "lat": 12.941988,
      "lon": 77.615438
    },
    {
      "timestamp": "2023-12-02T11:17:44",
      "lat": 12.941835,
      "lon": 77.615763
    },
    {
      "timestamp": "2023-12-02T11:18:01",
      "lat": 12.941777,
      "lon": 77.61612
    },
    {
      "timestamp": "2023-12-02T11:18:21",
      "lat": 12.941489,
      "lon": 77.616212
    },
    {
      "timestamp": "2023-12-02T11:18:36",
      "lat": 12.941442,
      "lon": 77.616554
    },
    {
      "timestamp": "2023-12-02T11:18:52",
      "lat": 12.941413,
      "lon": 77.616915
    },
    {
      "timestamp": "2023-12-02T11:19:09",
      "lat": 12.941384,
      "lon": 77.617276
    },
    {
      "timestamp": "2023-12-02T11:19:29",
      "lat": 12.941082,
      "lon": 77.617316
    },
    {
      "timestamp": "2023-12-02T11:19:48",
      "lat": 12.941087,
      "lon": 77.617678
    },
    {
      "timestamp": "2023-12-02T11:20:09",
      "lat": 12.941049,
      "lon": 77.618037
    },
    {
      "timestamp": "2023-12-02T11:20:34",
      "lat": 12.940959,
      "lon": 77.618388
    },
    {
      "timestamp": "2023-12-02T11:20:50",
      "lat": 12.94081,
      "lon": 77.618717
    },
    {
      "timestamp": "2023-12-02T11:21:11",
      "lat": 12.940652,
      "lon": 77.619043
    },
    {
      "timestamp": "2023-12-02T11:21:36",
      "lat": 12.940671,
      "lon": 77.61932
    },
    {
      "timestamp": "2023-12-02T11:21:55",
      "lat": 12.94087,
      "lon": 77.619547
    },
    {
      "timestamp": "2023-12-02T11:22:14",
      "lat": 12.940699,
      "lon": 77.619866
    },
    {
      "timestamp": "2023-12-02T11:22:39",
      "lat": 12.940529,
      "lon": 77.620186
    },
    {
      "timestamp": "2023-12-02T11:22:55",
      "lat": 12.940322,
      "lon": 77.620477
    },
    {
      "timestamp": "2023-12-02T11:23:10",
      "lat": 12.940063,
      "lon": 77.62073
    },
    {
      "timestamp": "2023-12-02T11:23:31",
      "lat": 12.940242,
      "lon": 77.620555
    },
    {
      "timestamp": "2023-12-02T11:23:55",
      "lat": 12.940467,
      "lon": 77.620279
    },
    {
      "timestamp": "2023-12-02T11:24:11",
      "lat": 12.940646,
      "lon": 77.619964
    },
    {
      "timestamp": "2023-12-02T11:24:36",
      "lat": 12.940817,
      "lon": 77.619645
    },
    {
      "timestamp": "2023-12-02T11:24:52",
      "lat": 12.940764,
      "lon": 77.619382
    },
    {
      "timestamp": "2023-12-02T11:25:12",
      "lat": 12.940603,
      "lon": 77.619143
    },
    {
      "timestamp": "2023-12-02T11:25:33",
      "lat": 12.940762,
      "lon": 77.618818
    },
    {
      "timestamp": "2023-12-02T11:25:55",
      "lat": 12.94092,
      "lon": 77.618492
    },
    {
      "timestamp": "2023-12-02T11:26:13",
      "lat": 12.941021,
      "lon": 77.618145
    },
    {
      "timestamp": "2023-12-02T11:26:38",
      "lat": 12.941084,
      "lon": 77.617789
    },
    {
      "timestamp": "2023-12-02T11:27:02",
      "lat": 12.941084,
      "lon": 77.617427
    },
    {
      "timestamp": "2023-12-02T11:27:26",
      "lat": 12.94133,
      "lon": 77.617334
    },
    {
      "timestamp": "2023-12-02T11:27:48",
      "lat": 12.941404,
      "lon": 77.617026
    },
    {
      "timestamp": "2023-12-02T11:28:12",
      "lat": 12.941433,
      "lon": 77.616665
    },
    {
      "timestamp": "2023-12-02T11:28:35",
      "lat": 12.941461,
      "lon": 77.616304
    },
    {
      "timestamp": "2023-12-02T11:28:57",
      "lat": 12.941739,
      "lon": 77.616199
    },
    {
      "timestamp": "2023-12-02T11:29:21",
      "lat": 12.941812,
      "lon": 77.615872
    },
    {
      "timestamp": "2023-12-02T11:29:41",
      "lat": 12.941934,
      "lon": 77.615536
    },
    {
      "timestamp": "2023-12-02T11:29:57",
      "lat": 12.94211,
      "lon": 77.615219
    },
    {
      "timestamp": "2023-12-02T11:30:13",
      "lat": 12.94225,
      "lon": 77.614885
    },
    {
      "timestamp": "2023-12-02T11:30:36",
      "lat": 12.942412,
      "lon": 77.614561
    },
    {
      "timestamp": "2023-12-02T11:30:56",
      "lat": 12.942572,
      "lon": 77.614236
    },
    {
      "timestamp": "2023-12-02T11:31:13",
      "lat": 12.942714,
      "lon": 77.613904
    },
    {
      "timestamp": "2023-12-02T11:31:29",
      "lat": 12.942824,
      "lon": 77.613559
    },
    {
      "timestamp": "2023-12-02T11:31:54",
      "lat": 12.942948,
      "lon": 77.613219
    },
    {
      "timestamp": "2023-12-02T11:32:10",
      "lat": 12.943131,
      "lon": 77.612914
    },
    {
      "timestamp": "2023-12-02T11:32:26",
      "lat": 12.943249,
      "lon": 77.612572
    },
    {
      "timestamp": "2023-12-02T11:32:47",
      "lat": 12.943348,
      "lon": 77.612224
    },
    {
      "timestamp": "2023-12-02T11:33:11",
      "lat": 12.943412,
      "lon": 77.611869
    },
    {
      "timestamp": "2023-12-02T11:33:33",
      "lat": 12.94347,
      "lon": 77.611513
    },
    {
      "timestamp": "2023-12-02T11:33:51",
      "lat": 12.943575,
      "lon": 77.611166
    },
    {
      "timestamp": "2023-12-02T11:34:12",
      "lat": 12.943699,
      "lon": 77.610828
    },
    {
      "timestamp": "2023-12-02T11:34:33",
      "lat": 12.943881,
      "lon": 77.610515
    },
    {
      "timestamp": "2023-12-02T11:34:49",
      "lat": 12.943956,
      "lon": 77.610161
    },
    {
      "timestamp": "2023-12-02T11:35:08",
      "lat": 12.944039,
      "lon": 77.609808
    },
    {
      "timestamp": "2023-12-02T11:35:23",
      "lat": 12.944114,
      "lon": 77.609455
    },
    {
      "timestamp": "2023-12-02T11:35:39",
      "lat": 12.944151,
      "lon": 77.609096
    },
    {
      "timestamp": "2023-12-02T11:35:57",
      "lat": 12.944068,
      "lon": 77.608858
    },
    {
      "timestamp": "2023-12-02T11:36:14",
      "lat": 12.943993,
      "lon": 77.608585
    },
    {
      "timestamp": "2023-12-02T11:36:36",
      "lat": 12.94401,
      "lon": 77.608223
    },
    {
      "timestamp": "2023-12-02T11:36:58",
      "lat": 12.944006,
      "lon": 77.607867
    },
    {
      "timestamp": "2023-12-02T11:37:23",
      "lat": 12.944001,
      "lon": 77.607505
    },
    {
      "timestamp": "2023-12-02T11:37:44",
      "lat": 12.94399,
      "lon": 77.607143
    },
    {
      "timestamp": "2023-12-02T11:38:00",
      "lat": 12.943975,
      "lon": 77.606781
    },
    {
      "timestamp": "2023-12-02T11:38:23",
      "lat": 12.943955,
      "lon": 77.606419
    },
    {
      "timestamp": "2023-12-02T11:38:41",
      "lat": 12.943947,
      "lon": 77.606058
    },
    {
      "timestamp": "2023-12-02T11:38:59",
      "lat": 12.943998,
      "lon": 77.6057
    },
    {
      "timestamp": "2023-12-02T11:39:19",
      "lat": 12.944056,
      "lon": 77.605342
    },
    {
      "timestamp": "2023-12-02T11:39:36",
      "lat": 12.944114,
      "lon": 77.604984
    },
    {
      "timestamp": "2023-12-02T11:39:51",
      "lat": 12.944172,
      "lon": 77.604627
    },
    {
      "timestamp": "2023-12-02T11:40:13",
      "lat": 12.944219,
      "lon": 77.604268
    },
    {
      "timestamp": "2023-12-02T11:40:30",
      "lat": 12.944249,
      "lon": 77.603907
    },
    {
      "timestamp": "2023-12-02T11:40:54",
      "lat": 12.944279,
      "lon": 77.603546
    },
    {
      "timestamp": "2023-12-02T11:41:19",
      "lat": 12.944311,
      "lon": 77.603186
    },
    {
      "timestamp": "2023-12-02T11:41:35",
      "lat": 12.944339,
      "lon": 77.602825
    },
    {
      "timestamp": "2023-12-02T11:41:53",
      "lat": 12.944024,
      "lon": 77.602809
    },
    {
      "timestamp": "2023-12-02T11:42:17",
      "lat": 12.943663,
      "lon": 77.602835
    },
    {
      "timestamp": "2023-12-02T11:42:32",
      "lat": 12.943301,
      "lon": 77.602849
    },
    {
      "timestamp": "2023-12-02T11:42:50",
      "lat": 12.943285,
      "lon": 77.602599
    },
    {
      "timestamp": "2023-12-02T11:43:09",
      "lat": 12.943402,
      "lon": 77.602257
    },
    {
      "timestamp": "2023-12-02T11:43:34",
      "lat": 12.94319,
      "lon": 77.602078
    },
    {
      "timestamp": "2023-12-02T11:43:53",
      "lat": 12.943226,
      "lon": 77.601771
    },
    {
      "timestamp": "2023-12-02T11:44:15",
      "lat": 12.942959,
      "lon": 77.601616
    },
    {
      "timestamp": "2023-12-02T11:44:40",
      "lat": 12.943049,
      "lon": 77.601285
    },
    {
      "timestamp": "2023-12-02T11:45:02",
      "lat": 12.943286,
      "lon": 77.601017
    },
    {
      "timestamp": "2023-12-02T11:45:23",
      "lat": 12.943516,
      "lon": 77.600737
    },
    {
      "timestamp": "2023-12-02T11:45:42",
      "lat": 12.943579,
      "lon": 77.600389
    },
    {
      "timestamp": "2023-12-02T11:46:01",
      "lat": 12.943677,
      "lon": 77.600116
    },
    {
      "timestamp": "2023-12-02T11:46:22",
      "lat": 12.943922,
      "lon": 77.599982
    },
    {
      "timestamp": "2023-12-02T11:46:43",
      "lat": 12.943996,
      "lon": 77.599627
    },
    {
      "timestamp": "2023-12-02T11:47:06",
      "lat": 12.944273,
      "lon": 77.599589
    },
    {
      "timestamp": "2023-12-02T11:47:22",
      "lat": 12.944614,
      "lon": 77.599708
    },
    {
      "timestamp": "2023-12-02T11:47:44",
      "lat": 12.944955,
      "lon": 77.599832
    },
    {
      "timestamp": "2023-12-02T11:48:03",
      "lat": 12.945292,
      "lon": 77.599964
    },
    {
      "timestamp": "2023-12-02T11:48:26",
      "lat": 12.945628,
      "lon": 77.6001
    },
    {
      "timestamp": "2023-12-02T11:48:51",
      "lat": 12.945965,
      "lon": 77.600232
    },
    {
      "timestamp": "2023-12-02T11:49:16",
      "lat": 12.946304,
      "lon": 77.600357
    },
    {
      "timestamp": "2023-12-02T11:49:39",
      "lat": 12.946641,
      "lon": 77.600492
    },
    {
      "timestamp": "2023-12-02T11:49:59",
      "lat": 12.946982,
      "lon": 77.600612
    },
    {
      "timestamp": "2023-12-02T11:50:23",
      "lat": 12.947327,
      "lon": 77.600722
    },
    {
      "timestamp": "2023-12-02T11:50:48",
      "lat": 12.947672,
      "lon": 77.600832
    },
    {
      "timestamp": "2023-12-02T11:51:06",
      "lat": 12.947629,
      "lon": 77.60113
    },
    {
      "timestamp": "2023-12-02T11:51:27",
      "lat": 12.947605,
      "lon": 77.60142
    },
    {
      "timestamp": "2023-12-02T11:51:48",
      "lat": 12.94794,
      "lon": 77.601555
    },
    {
      "timestamp": "2023-12-02T11:52:13",
      "lat": 12.948274,
      "lon": 77.601692
    },
    {
      "timestamp": "2023-12-02T11:52:38",
      "lat": 12.948484,
      "lon": 77.601944
    },
    {
      "timestamp": "2023-12-02T11:53:02",
      "lat": 12.948495,
      "lon": 77.602301
    },
    {
      "timestamp": "2023-12-02T11:53:24",
      "lat": 12.94843,
      "lon": 77.602619
    },
    {
      "timestamp": "2023-12-02T11:53:42",
      "lat": 12.948766,
      "lon": 77.602754
    },
    {
      "timestamp": "2023-12-02T11:53:58",
      "lat": 12.949099,
      "lon": 77.602895
    },
    {
      "timestamp": "2023-12-02T11:54:19",
      "lat": 12.949437,
      "lon": 77.603026
    },
    {
      "timestamp": "2023-12-02T11:54:43",
      "lat": 12.949776,
      "lon": 77.603153
    },
    {
      "timestamp": "2023-12-02T11:55:00",
      "lat": 12.950106,
      "lon": 77.603301
    },
    {
      "timestamp": "2023-12-02T11:55:23",
      "lat": 12.950453,
      "lon": 77.603404
    },
    {
      "timestamp": "2023-12-02T11:55:48",
      "lat": 12.950801,
      "lon": 77.6035
    },
    {
      "timestamp": "2023-12-02T11:56:04",
      "lat": 12.951141,
      "lon": 77.603622
    },
    {
      "timestamp": "2023-12-02T11:56:28",
      "lat": 12.95146,
      "lon": 77.603794
    },
    {
      "timestamp": "2023-12-02T11:56:52",
      "lat": 12.951777,
      "lon": 77.603968
    },
    {
      "timestamp": "2023-12-02T11:57:14",
      "lat": 12.952095,
      "lon": 77.604143
    },
    {
      "timestamp": "2023-12-02T11:57:36",
      "lat": 12.952322,
      "lon": 77.604412
    },
    {
      "timestamp": "2023-12-02T11:58:01",
      "lat": 12.952491,
      "lon": 77.604732
    },
    {
      "timestamp": "2023-12-02T11:58:19",
      "lat": 12.952661,
      "lon": 77.605051
    },
    {
      "timestamp": "2023-12-02T11:58:36",
      "lat": 12.952895,
      "lon": 77.605278
    },
    {
      "timestamp": "2023-12-02T11:58:56",
      "lat": 12.953255,
      "lon": 77.605323
    },
    {
      "timestamp": "2023-12-02T11:59:15",
      "lat": 12.953614,
      "lon": 77.605369
    },
    {
      "timestamp": "2023-12-02T11:59:38",
      "lat": 12.953973,
      "lon": 77.605414
    },
    {
      "timestamp": "2023-12-02T12:00:03",
      "lat": 12.954332,
      "lon": 77.60546
    },
    {
      "timestamp": "2023-12-02T12:00:18",
      "lat": 12.954692,
      "lon": 77.605505
    },
    {
      "timestamp": "2023-12-02T12:00:37",
      "lat": 12.95505,
      "lon": 77.605559
    },
    {
      "timestamp": "2023-12-02T12:00:52",
      "lat": 12.955407,
      "lon": 77.605619
    },
    {
      "timestamp": "2023-12-02T12:01:11",
      "lat": 12.955651,
      "lon": 77.60576
    },
    {
      "timestamp": "2023-12-02T12:01:26",
      "lat": 12.95579,
      "lon": 77.605978
    },
    {
      "timestamp": "2023-12-02T12:01:43",
      "lat": 12.955863,
      "lon": 77.606289
    },
    {
      "timestamp": "2023-12-02T12:02:03",
      "lat": 12.955829,
      "lon": 77.606649
    },
    {
      "timestamp": "2023-12-02T12:02:28",
      "lat": 12.955797,
      "lon": 77.60701
    },
    {
      "timestamp": "2023-12-02T12:02:51",
      "lat": 12.955768,
      "lon": 77.607371
    },
    {
      "timestamp": "2023-12-02T12:03:12",
      "lat": 12.95558,
      "lon": 77.607532
    },
    {
      "timestamp": "2023-12-02T12:03:29",
      "lat": 12.955221,
      "lon": 77.607479
    },
    {
      "timestamp": "2023-12-02T12:03:53",
      "lat": 12.955133,
      "lon": 77.607784
    },
    {
      "timestamp": "2023-12-02T12:04:10",
      "lat": 12.955084,
      "lon": 77.608143
    },
    {
      "timestamp": "2023-12-02T12:04:32",
      "lat": 12.955036,
      "lon": 77.608502
    },
    {
      "timestamp": "2023-12-02T12:04:53",
      "lat": 12.954989,
      "lon": 77.608861
    },
    {
      "timestamp": "2023-12-02T12:05:17",
      "lat": 12.954942,
      "lon": 77.60922
    },
    {
      "timestamp": "2023-12-02T12:05:33",
      "lat": 12.95468,
      "lon": 77.609444
    },
    {
      "timestamp": "2023-12-02T12:05:50",
      "lat": 12.954377,
      "lon": 77.609643
    },
    {
      "timestamp": "2023-12-02T12:06:12",
      "lat": 12.954307,
      "lon": 77.609959
    },
    {
      "timestamp": "2023-12-02T12:06:32",
      "lat": 12.954382,
      "lon": 77.610312
    },
    {
      "timestamp": "2023-12-02T12:06:56",
      "lat": 12.95442,
      "lon": 77.610661
    },
    {
      "timestamp": "2023-12-02T12:07:17",
      "lat": 12.954323,
      "lon": 77.61101
    },
    {
      "timestamp": "2023-12-02T12:07:41",
      "lat": 12.954224,
      "lon": 77.611358
    },
    {
      "timestamp": "2023-12-02T12:08:06",
      "lat": 12.954025,
      "lon": 77.61156
    },
    {
      "timestamp": "2023-12-02T12:08:22",
      "lat": 12.953791,
      "lon": 77.611662
    }
  ]
}